{
  "androidMinimumVersion": 1,
  "androidMinimumVersionMessage": "Om de app te gebruiken heb je de laatste versie uit de store nodig.",
  "playStoreURL": "https://play.google.com/store/apps/details?id=nl.rijksoverheid.dcbs.verifier",
  "iosMinimumVersion": "1.0.0",
  "iosMinimumVersionMessage": "Om de app te gebruiken heb je de laatste versie uit de store nodig.",
  "iosAppStoreURL": "https://apps.apple.com/nl/app/dcc-scanner-app/id1572642859",
  "appDeactivated": false,
  "configTTL": 3600,
  "maxValidityHours": 40,
  "informationURL": "https://www.rijksoverheid.nl/ministeries/ministerie-van-infrastructuur-en-waterstaat",
  "domesticVerificationRules": {
    "qrValidForSeconds": 180
  },
  "europeanVerificationRules": {
    "testAllowedTypes": [
      "LP217198-3",
      "LP6464-4"
    ],
    "testValidityHours": 40,
    "vaccineAllowedProducts": [
      "EU/1/20/1528",
      "EU/1/20/1507",
      "EU/1/21/1529",
      "EU/1/20/1525",
      "Covishield",
      "BBIBP-CorV",
      "CoronaVac",
      "Covaxin"
    ],
    "recoveryValidFromDays": 11,
    "recoveryValidUntilDays": 180,
    "vocExtraTestRule": {
      "enabled": true,
      "singlePCRTestHours": 24,
      "secondDosePCRMinTestHours": 48,
      "secondDoseAntiGenMinTestHours": 24
    },
    "proofIdentifierDenylist": {
      "q5TKp3sKMWlVjmMUGdhTtw==": true,
      "ljOsYiw6IDXfndOeyUfTNg==": true,
      "Cd4kRRFnM23JNNHCQ9m7ag==": true,
      "NM39YohV4lo3JapOxPqb2g==": true,
      "pjpI2WGn+/0pyrNsZUs8Yg==": true,
      "jWeVvZ/LPgFjFIzKffSbDQ==": true,
      "QsuadE0oH0+H0A3I/cevWQ==": true,
      "YZ9nsv9RR9hu19sb2mPvSA==": true,
      "pwtNZ4y7dPb6b7lQPU3mRQ==": true,
      "SGVlZlQFSWQbONbuH5pz4g==": true,
      "++Y5vMxilCkbQ3gaSldSCg==": true,
      "+4dHIiH0gYn0bpKs+3zxwA==": true,
      "+7BGMtMdyH6iDuRTVtNFtA==": true,
      "+882w4YXlyLZgffqgPrycw==": true,
      "+AXhHeMQI/rneALNZMktVg==": true,
      "+EqUdTxEkTd2uD8TxrX0nQ==": true,
      "+LSN1wO4PHCIqaSdttlKQg==": true,
      "+WCDriUPqr/ImBgAWik7aQ==": true,
      "+blt6iBQBmLN3qLvCsHwgA==": true,
      "+bpu+O9mYPuWnbs4Z86inA==": true,
      "+vWIaJ6H5xPuqr+Ryh8lGw==": true,
      "/0okOICuoE54zf0fzN1q1w==": true,
      "/2puF0Hdu+xB1F/9w4JuSA==": true,
      "/3Qd/ez9+EN2P8I92NiDpA==": true,
      "/4RQG2LpzpDCsyE0K/9mRg==": true,
      "/AljcHkNXSA2yNFWECv14g==": true,
      "/CV7z3rwMJsSidZfuSe/SA==": true,
      "/E4jc5iTiJ8trwb77cDzrg==": true,
      "/JRoberNe+vzDsuGbQckzA==": true,
      "/KmMyEj0K/uk5fJWpQ7mpA==": true,
      "/LAIKs5Q4DAtFqh02i3VSA==": true,
      "/ODOTm6FhgsF0ezKRPWisg==": true,
      "/SehjCIyeSz1qPLr7IywYQ==": true,
      "/Uvv3pbxejNBWwCBMHSidg==": true,
      "/b7dX+7czE2RUPNIfi6Cig==": true,
      "/ePDBm9xQ9dYiwN4Iv4PWA==": true,
      "/q83WBSYMU1U4v5QlehV4Q==": true,
      "/r+8sOJ4BRAdc5mylJ3dRg==": true,
      "/wJdk1IiKSAhcYXvZQxJYw==": true,
      "/wMq1J3hmBu+lmWJ6i07nw==": true,
      "030vhHRi1XVBAcuRxpApEQ==": true,
      "03xBKHs++T21xpbucWjfeQ==": true,
      "041wynLt3oiAqrQehCE/vQ==": true,
      "04RcQRHevoqjvNbMlelx1g==": true,
      "07uXYwZUM109mBRiK1Xp/g==": true,
      "083skQbOct7zQnYskYdmPw==": true,
      "087kx/0eWa9ekmcgpIwVGQ==": true,
      "0Mx5EL2AaUMknMIdTX9xQw==": true,
      "0O5FK/7zj3TovySRNOjjaA==": true,
      "0QGO7L4O/4UYuegoSgB66g==": true,
      "0Y2lE7RFspTh6OVG0gn3QQ==": true,
      "0b/1fxqStLJNRnBiv3kWbw==": true,
      "0kVYvAUr4pGt2KXfjJOJDA==": true,
      "0nyf4tGQ/xubh/cVoR8t+g==": true,
      "0oicyhfPMuvhSZTFwCO11w==": true,
      "0rfCiFgYBk3kUGjqRfrURQ==": true,
      "0wI3+E2NIkV38+Hue3t4Ag==": true,
      "0wfiW6+VokzrgtuHD6wqVA==": true,
      "108kwaUP1GfSAqG/2Py/Jg==": true,
      "13MDWeSfR05F/oT2TWKo3A==": true,
      "14k75pCvjbYwKXcIv8Rd3A==": true,
      "1V5KLsccYgj13hBEnpHq9A==": true,
      "1VAoggL1y7hx0xE6iBHljw==": true,
      "1XiGW/EmMsmj1sEe30j32Q==": true,
      "1ZecTGXP9+8FEkHpKz7Cxw==": true,
      "1cwqI/SewmYBdLPv+89QAw==": true,
      "1dxtBLRZH4vUXQhJJtD0iQ==": true,
      "1iAW7HlgagWjCjl91tOXBA==": true,
      "1wWEvlYDutTd39U9LvK3PQ==": true,
      "24PjdOXE+EqWyzSVzmRRSA==": true,
      "262eY3iFsqB9EYGi1Ii0dg==": true,
      "28OfA7nYxq7F3nGd2zOMag==": true,
      "29O2yzJZoxxy43Ozz+cNOg==": true,
      "2DJzgZtyx7MvZC481obRgA==": true,
      "2FSNowQkf5c/rpMOIXtomA==": true,
      "2Gk7FmdNnNhuh08pWX31qQ==": true,
      "2JomP8rBFBqnhFANfooKCQ==": true,
      "2MgOkUj5EZaWLi66RGkHkw==": true,
      "2N7dRHUxS/dk3TWlsv8nug==": true,
      "2O7ivLQ9FjU8QxiigpQEzQ==": true,
      "2PlMhoWM6uFRGMprFk3oPg==": true,
      "2Ue0JWB7PTQp0SEHi6HFKg==": true,
      "2bGwy+RG4wToO8DjVrLtYg==": true,
      "2dc2V63Nd3SN2RsuOCCRXA==": true,
      "2l45FoEOIHQyj0kj7L266g==": true,
      "2paqb8lxFWgNgJwy4Y27KA==": true,
      "2rrpRiOk5zq5w/vVLSwx4g==": true,
      "2sBPQx6eiLbLNEepmKixCw==": true,
      "2sWWqVHo/nw4QeO1qmvUmA==": true,
      "2wCfsjSug80MXmt0B2LApQ==": true,
      "3+D1QXWujGY73H9Sc4swvg==": true,
      "3+pR1tZV/T71MSj4j2lNZQ==": true,
      "33GjtQnCXETMlyrO+V16Jw==": true,
      "34/feDWN3OGaIDuo4BY/hw==": true,
      "3HK3UdswlDWkvQYv52EunQ==": true,
      "3IkFFUJRkeizjqGKYxvKAw==": true,
      "3JVYFhq5aiwMmsfZxDLWAg==": true,
      "3LqevzLNDavA8ML+93mEbA==": true,
      "3NlmkIy9dL+B3id9nhtCTA==": true,
      "3XG4UbY9sbk1qeUDcoqHiw==": true,
      "3XYC1TbNB+HVQFgB1UzIbA==": true,
      "3Y5PrVhBoJNwLqRS2RyAcQ==": true,
      "3iLD1tT4F9gIYQ+gz9dT9g==": true,
      "3lPI1t3eSCSrPdMpGecmCg==": true,
      "3mtz2OUKqaJ0FBZ4D2H3pg==": true,
      "3n5d+hriZ+UV5NQwSbekQw==": true,
      "3zcPFbElAcyCkgWkF+OTPg==": true,
      "45LKR9vcddpyN2MVN1Nx3w==": true,
      "4Dq7NeogAoOr8cXjJFlO4w==": true,
      "4Gb4ouyG/HEBR5fj5AsnLg==": true,
      "4LP4XgwuU6DUcHNdeGDv4Q==": true,
      "4UQ/b/QV9ZZKYDHk+da0iw==": true,
      "4XyPB+gk6TdaJ5wWY4yAUQ==": true,
      "4isIL2M/m+llK3YeS+g0Wg==": true,
      "4k/2LZCNXsR1wyyV1yn4bw==": true,
      "4pnVAYSzygy+6l9Xsza00Q==": true,
      "4qqjELqvZ1YMS13VPGABtA==": true,
      "5/d61rx2DDhISOUGZ2Vtig==": true,
      "55HT62hegMmSwaTMdo2KwQ==": true,
      "576Bxzh7BgcNuOfOZZbr+Q==": true,
      "5ASW0f+3Mockt/Bjr9bAcw==": true,
      "5FwYmX22a0wCB++VVkCTQQ==": true,
      "5JtdqtrauYcDJayWgyqQTw==": true,
      "5MQ5Y0NIJoFC/HwkjQv1AQ==": true,
      "5OURvXUNQ/9t+F1zfCZ+lg==": true,
      "5QiAx4HxpSOqImNXsoz0RQ==": true,
      "5T3rHOMmLKEYbT/b4PtIow==": true,
      "5U86UWxEFRioHqJ/kQDe6g==": true,
      "5bLaVXEmYheknh96a9bQEw==": true,
      "5f09JLVpT3JHPK7oHe0RYQ==": true,
      "5gOVlGmHGVgmHJ1rb4b3eA==": true,
      "5jhG0pccagixY3NHoIf3VA==": true,
      "5k0elB42VacT8asjyhmrpA==": true,
      "5kHGe+vrdvb9Svo6+Ir7Hw==": true,
      "5tNC7EL7wqa8p/5DQGRK7g==": true,
      "6+i3vdcgDJiOEvaW5D415w==": true,
      "65oxdzAPwHOXnfzHA0gRMA==": true,
      "6BQ2S6lLWE+7Qr4Zuwvwzg==": true,
      "6EkJmJLPI2A0kMjAbssgRQ==": true,
      "6HB8nwkzCZmIhio/PiSN/w==": true,
      "6MCrF/63TjNlQcQ27/1Tbw==": true,
      "6PcPPZXbWrtcKNMz1+y1jQ==": true,
      "6Wz1wBucguP5myMNPfUQ4A==": true,
      "6X0bl+0f3sDDyVd15gykTQ==": true,
      "6dpikaClXvVeSmM8oy50Lw==": true,
      "6er7om/WIz7mwziBDiH18g==": true,
      "6j8t9vgoISt9rZsiR68W0A==": true,
      "6m0ncb375WiKeRD4Z3VewQ==": true,
      "6twN3dkCtSwpzsO5JvTyxg==": true,
      "6ueYaexRouHyAYujYvhA3w==": true,
      "6xdNO8ID0Bduxn2YRVQCqQ==": true,
      "7+Kk8KZif4BmIe/YWy3hrQ==": true,
      "7+eG0nTkLMkQI0mtNtI3iw==": true,
      "750WrUcOwttNFo5VefxRjg==": true,
      "79gyG93PaaXWdXvjY6bO0Q==": true,
      "7Inqj4N/ZfLlmKJoLtZmyg==": true,
      "7K/RbMsUqa6tW+zBUghBBQ==": true,
      "7N1FAghXsVL94YELc4vSkw==": true,
      "7OcNZRLDs4NgO9jvMdjR/g==": true,
      "7XPZilP+2p2JVgvDFiKImQ==": true,
      "7dOoef+yKKkqQy+9VQvgfg==": true,
      "7f6NhJdIkVuZY70CLvW5bA==": true,
      "7fxlNZdqWmxJcMNhLcLpkw==": true,
      "7ms5GEaHvqc0mm0CO5SeqQ==": true,
      "7qM52Rjyo6rFo4VyiFHZWw==": true,
      "8/lvTwB4I/jphIw99pEQgw==": true,
      "81hakRe6PrhU5DnaMOdlDA==": true,
      "865Gk1aUyGlJCN3E0mkogw==": true,
      "8DyTmVdN2CaTbOEBzFG/gA==": true,
      "8EdbSZwcTI+gFLdWwafACg==": true,
      "8RjhzRyjq73CxXxm87DeuQ==": true,
      "8bqKoN3seB3KgwloHTQYBw==": true,
      "8gPWa/V2259gJ689ITY1bQ==": true,
      "8jN0Jin92qISosjt7OTWzg==": true,
      "8jk1BQAEFbPwwIonaMNntg==": true,
      "8kPJgcJ93MG9N20Y4fV5iQ==": true,
      "8mXWrZN4/mZFmBgToPhOhQ==": true,
      "8mzbDiqkiwMApSOKGfGBzQ==": true,
      "8o9yg1hNXTNysF65hGvqXA==": true,
      "8omUvfTNkhbylFYWn/FoAw==": true,
      "8pOyHopf5JlrR0lMs1JvOg==": true,
      "8q+jJ8tnONLmiAxumgGSSA==": true,
      "8vHLPO811HNcA9LEPQPrUQ==": true,
      "8xLyI1OysOIePk0UE6Dr2w==": true,
      "93gLKh0CoHAD7RKDPMWtAQ==": true,
      "94BF88CyQ52bzW+AiYMDuQ==": true,
      "9EIurDtmCiYQu57OgYtpUQ==": true,
      "9GJPB5R5iTelisXfxEy7QQ==": true,
      "9H4R20asaKAkQjuOzlgo1g==": true,
      "9N7AizJvTGa/01sGayAStA==": true,
      "9OyYf/1P2z+0BY3LgkFxKQ==": true,
      "9Yg+IouNCbVpaQeOu7VEIw==": true,
      "9deVsdrmxeN+AxRKlKaD7Q==": true,
      "9lcIW3oMzYb1DQMP17JwtQ==": true,
      "9mg46MPgPYI6Z4A/kPulcA==": true,
      "9reHTRgyBs8+2qbLpTUyMg==": true,
      "9snRPzChuqzcEN5FH9O1AA==": true,
      "A+INojt70pnS51zOhQj4Aw==": true,
      "A+QzBCAAAMwOjTTYUQXfRw==": true,
      "A1Wdt9NjV04AFglyjmxvMg==": true,
      "A8TafX42WiC5FXtnfIUJBg==": true,
      "A9Wb73Deut/D3vlf24byEA==": true,
      "ABhFpte6Ze+VPGDiR0dZ+A==": true,
      "ADF+GQL69NP1JEpZxXPdTw==": true,
      "AJypezBFR9YkDTJRy78LdA==": true,
      "ANZWumXBY10bKN4hgE68Gw==": true,
      "ANxeLs4hNt4ORWoNRpv7xQ==": true,
      "APX5neC5xI03kyBB/G7SpQ==": true,
      "AWQXsLws4f8ggbIut/6dlA==": true,
      "AbO5eCamJSQ+o+Bj/Za3vA==": true,
      "AcjDUGGthV47GW/RWJGNeA==": true,
      "Ad0WSNxE1XEqiJyqbllbcg==": true,
      "AdSicEIOElOWU5esV4pu3A==": true,
      "Aekf+44dtLQBMLSTRcb+7g==": true,
      "AgHUwsEkofdwgWQcrSMMUg==": true,
      "Ah8M22tdEeNgj957myqNJg==": true,
      "AyZxZA5EG9fLo3IyLdHgyQ==": true,
      "B/eklU0YPa9PiWgDUXsp0g==": true,
      "B2EL2Z8Wz2Kcf1nEL3/7KA==": true,
      "B3B12jlABvzjnlEKF7AL9w==": true,
      "BE5QqRyouFg1/qwNPhLp7A==": true,
      "BI5Xlno0HWwol+oUCmtp5g==": true,
      "BIVYUU0ZR2NCRnIzZ20cxA==": true,
      "BJjlR7qVPpymtLwGLY12Jw==": true,
      "BLdjpN7MYUqUkQw7sK7qMw==": true,
      "BMcVbhVZ4GwgSCu3fC2fmA==": true,
      "BOnXlVV9cijLVWaB74gkWw==": true,
      "BP6Q/pwWfLTsaYTlyo+vqQ==": true,
      "BUqCCbXTuJVGXiJpoYbX1g==": true,
      "BVkn/VpvWfZHSIDXWVQlUw==": true,
      "BXcIf8qrVB3+yeHumHT2ig==": true,
      "BaHIkmSlfu2GqtrL0Fphww==": true,
      "BckgTbvxD/aqbOsWr11VtQ==": true,
      "BdEP+yIVhbSBD6pLO1ABxQ==": true,
      "C+8xuVzSLauhWkQkyqSNkg==": true,
      "C9qtgaSF51/k7By990QHYg==": true,
      "CHk/sWLx37U0BWMoaHRm7Q==": true,
      "CM7YYsYdRpYjZvB6302oOQ==": true,
      "COBGuWzRj36t9Q34ydXBFg==": true,
      "CStU+bNTnvqVJ0eckoSVoQ==": true,
      "CXGHA5TQyyRd9Vlyo6MXcw==": true,
      "CZqvDtNL1csp2CYK5GHpXw==": true,
      "Ccsp72+JwTlo93ay7HXGkA==": true,
      "CdTByfaiKE6+VHyuYj5MRg==": true,
      "Cg13ct9KXlANAVGdZ0K2UA==": true,
      "Ci9g3XED8RBz3kQp+As7fg==": true,
      "CicwVrXjpofhAdIlxqzVfw==": true,
      "CpwhALF7HW9WeAwVnXcM1g==": true,
      "CscmEcmI2xUCVo+J/I0MmQ==": true,
      "CxkJeI7GEUdXsEJNF+AU3A==": true,
      "CyXSgEUMUe0XeJMR0Cf9qw==": true,
      "D+y/NrSMeDAKhKNGvJfrRA==": true,
      "D6c5kHTnVfpAze3VoSHRKA==": true,
      "D7iHTgMhTbyYCujb0/zHGw==": true,
      "DBLQDtSdfkbtQt4nwHwYKw==": true,
      "DHywHBSm8LsjZyMPGtz8Ew==": true,
      "DJ2x3VoT7U4H6qTUIFehzQ==": true,
      "DYwaBL9tTvFo+wMCjMF9dA==": true,
      "DdgD6i5+hoHJBG7t4QrGUg==": true,
      "Dgtf6Qi8Tb99wnLTfAeOyQ==": true,
      "Div+Syd0pkmdH45Rg82E3w==": true,
      "E/MXgurgKtPuw9TACwg/NQ==": true,
      "E5l3lB0HERSVlX+AepV/Nw==": true,
      "E5pe7mMEiW7jDQF5i4fSAA==": true,
      "E8AI4TlaSBcW6CoQLcz9MQ==": true,
      "EAea4ZS6pD4CrtU0i/tQhw==": true,
      "ECxXIFocHU17BvFCuOhH1A==": true,
      "EELLuOUoivT83ue0NeYjcQ==": true,
      "ENw6BICTHgleGo8WboYFBg==": true,
      "EO+IRTM1cNWBa0DSQRVYlw==": true,
      "ETJBjiJeZcU/un/a0SrPnQ==": true,
      "EXLIo5xq58iC5IGvInOJ8g==": true,
      "EXwt0RrlRLrq2J1PaK0+0Q==": true,
      "EctK2nxWiLgxS2BjjQPc/g==": true,
      "EevO58GcXVsbJ9t538K5Tg==": true,
      "EnBXqJMcdHmuit7blOsAhg==": true,
      "Eo2jKxfRriZkdKTxZ104Sw==": true,
      "EpaiQYOCbCJYv5V5t7pSfA==": true,
      "Eqif2fRFcalqD7tTEHPt9A==": true,
      "EuGeF2qYO+PkRLSupZWM/Q==": true,
      "EyjGK7Q9bkEXN5bLcsfxfA==": true,
      "F1KrpM6IRgOuSuAvXk+NCw==": true,
      "F1LZS5abqOyo20QrxvgHxA==": true,
      "F1Lw7qt2rvNQz7MfdY83OQ==": true,
      "F4KknKIiuwPd3uPHZU9a0g==": true,
      "F9mrTXNfPjP1Oe/zpH9kXg==": true,
      "FEqs17ofDht0s7LBtKIxAQ==": true,
      "FGWKR0clTEzIzcHOI5IqQA==": true,
      "FcNvHUbEc4XI7crbIVwGsQ==": true,
      "FjYTixnWejrJZiZyJFJwnA==": true,
      "Fm0x33pfVliqGnXYoSGTfA==": true,
      "G25twAEN/mjNgk8uBXprxg==": true,
      "G7ZYFruip/jMrM03cjQK4g==": true,
      "G9Khwv1dG0SckTI7/CrJJA==": true,
      "GDDf+blydDsdLmUYRtqz6Q==": true,
      "GFAmoq7RT/Ji3grZxSPVEA==": true,
      "GFMJ0lOS1wP97FUbdd8JVg==": true,
      "GGPnsFUokXDia2/kcbiQOw==": true,
      "GPW2Hm1R7xhJqCi5z0egZw==": true,
      "GUypcC5eKi+d8ft3W3W5GQ==": true,
      "GWiOsO42mwvkuHdZywaykw==": true,
      "GXz7X4L1s2cqD6f+asHmYQ==": true,
      "GcaE+Mip6bFz50mQPgzc7w==": true,
      "Gdv65xkKLBJt9whM1ZwVYA==": true,
      "Gkiu2ivi1Hv9Z8n5KDvEfQ==": true,
      "GrfMF/odj9qR2f9OFmfXCA==": true,
      "GtCbR9HZe2K64L8CRbtSVg==": true,
      "GwkpNoLt/3xzbDlaM3LwSw==": true,
      "Gx9Z6GJA7QNoiD6vv3/4Bg==": true,
      "Gyp0jHSy6E5gPoTjmz+Vuw==": true,
      "H0uU430Vy59sMGVXBCpkzA==": true,
      "HEIjB+AlTkwBTnSL59pIiw==": true,
      "HGimgOw/tVFBL0YD6de2Eg==": true,
      "HH/KW0csRJR8740UzvSCXw==": true,
      "HJ5tpLk/0zCgX+XRP1GHCA==": true,
      "HUan2JjTWTwZbGn6xkGNHQ==": true,
      "HUsaoWVp73NtV3Wh9bPSLw==": true,
      "HYsX1JyF6GKPYHFzuO9UEw==": true,
      "Hd6MmKe0niMjr38KfOOxqw==": true,
      "HgI3qVQtSnEYo3ARRN9byA==": true,
      "Hrn80XqqccSwFTgDJB3hPg==": true,
      "Hs7qxRrXUzxWS9A1whVVUw==": true,
      "Hs9etGqpXszN2cgXaJMzfA==": true,
      "HwJkd9/2AzCdzEkeDRjrHg==": true,
      "Hy0L5JigB297ooVGWnk19Q==": true,
      "I4fmTEqP5092VGOXaAsdQQ==": true,
      "I4pVXlUP/AsWa8lH+70O1A==": true,
      "I76bZD0rLO+UPbUZcmVbTQ==": true,
      "IBIMDjB+NtxRkgMV3dozIA==": true,
      "IGVp2ctHEIWQMmXRI9EuGg==": true,
      "IJGu9fI3clO7ngnM+ympVQ==": true,
      "IMicdZaNivXcKi1m4lMMtA==": true,
      "INt6sZgRS+TDT7BVGdAU6g==": true,
      "IWatm3VuGVx0yAl2mLTQdg==": true,
      "IXZkbGSg/MmpV4ZiGq1imA==": true,
      "IaqXm3PHRhhikNu5EogNuA==": true,
      "Im1shFMkG38bAJEMETyz3g==": true,
      "In2cwBzbua0jIHEDMfcPQA==": true,
      "IntrPPi4JqNNQCyM1cNpLA==": true,
      "IuBTek9MPx2Ywz5nI9Wi1w==": true,
      "Iz5IFFdgh8o3FVTfk9PKmQ==": true,
      "J6Pj1VW2JPqzj75FneDigA==": true,
      "J9PwY5xQlcaefHT1ZKChcQ==": true,
      "JAyPIZCxPmTwVqIT07RdLw==": true,
      "JBRNVvutiHQSmTz3dJOP6w==": true,
      "JG8ilbkWAbAKlscFhK4CeA==": true,
      "JKQQenqPGm4yRxpw6hBW7g==": true,
      "JKXIgQJ8shG4oHWKyy+0Ag==": true,
      "JRvbDMcnqOUP5eQl3oP9+Q==": true,
      "JVduepUS1n9p3c+zm0h57Q==": true,
      "JZsWovy9yj6a271nq6UtAg==": true,
      "JZtodZ24wC0NeB8xDoBQLQ==": true,
      "JdEZqX05zLT8pgSBYo/6eA==": true,
      "JffrE/92ZN5UgInYeIEurA==": true,
      "JmqqQ2tkQhuUElMmOCEYIA==": true,
      "Jwv8prPAqd8FUX/nDrzY5g==": true,
      "KGu6rXzYQPHQvViOES8PMw==": true,
      "KHsxsS9ZaSNHBwlvtYVbpg==": true,
      "KI0wIgdjWi191iJw11jW9w==": true,
      "KJmra8uiF5YTzE5FBWmIPw==": true,
      "KKQc4WlRcTf2EMiml/mmuw==": true,
      "KMcUr4HyImV/Vj+EuxoGYQ==": true,
      "KPPLUDalau3CpCEIRETqhQ==": true,
      "KQtcHXz1gOLrdYzq1nsxNA==": true,
      "KRRfbHVGpRgqAouEnmnwIw==": true,
      "KT6KLMx9etGHjzAsS2YFGg==": true,
      "KWW4b5wzPjcau9EYWN8BPQ==": true,
      "KXhxpXv5X7fu8NQ7QPoSNw==": true,
      "KZnC91sdpJ6TET43huYSxQ==": true,
      "Ke/0LO9UUk5fgvkJ8GaEwg==": true,
      "Klks/gLdlJwTOr7Mt8bFng==": true,
      "KpLVcXSBNGH+TG45f60dJQ==": true,
      "Ksq2El7G4VtUSSBN/3m+hA==": true,
      "L067JVUEgF0gYa5R9bSXGw==": true,
      "L0sJATMLO83njSTfOD6vTA==": true,
      "L4Df1fJJMWWoym3VA8998g==": true,
      "L6ccMidSMCwJc65L9g8/jw==": true,
      "L7gj3Re2v56uMxtU5HracA==": true,
      "L9IWvL+WotFzY/K6H/fWgg==": true,
      "LGTOovOZ02eno6VTHHY6cA==": true,
      "LNuxGEXQbOv34wrlGXel2g==": true,
      "LO/MyMuLxx6DwNa3PQFrxg==": true,
      "LPcY0E7CBRKsJ4nGrLQkHA==": true,
      "LQsZHDAr9BDJg74GZKcESw==": true,
      "LR9ZFR+q86NjeA2TfIz0sA==": true,
      "LS68A7Vak0Ek1lVfdjYSNA==": true,
      "Lasn3Kj+PCRVPIWPL8ZO/A==": true,
      "LfsERgr+q1/+rgk0cgRnXA==": true,
      "LpEIm22H2kTjysMed0JYMw==": true,
      "M2QmafDPOHDDw7inmp+kng==": true,
      "MDd4hbzi56Ty12mOl42fjQ==": true,
      "MGDvj30btCoKlDqylP76hQ==": true,
      "MI6z58AmvM5gWXLxPKhwGA==": true,
      "MLbSk2nhOTOrXFSuw86gSw==": true,
      "MNDl3vylAgAgWGYpRF6IZA==": true,
      "MQpS6Z89eHcWq5R/ozPM6Q==": true,
      "MUXL3lSzrN3tTpMxsWQI/A==": true,
      "MZltj+vR2nd3DvBMd1eSiA==": true,
      "MmF1JNCBwzU3fuTpyZhqQg==": true,
      "MrGsQzJGoODhcT4CW36oXA==": true,
      "MuKCbjdO+TzFxojKriLeMg==": true,
      "N5NIBMbC4XG6s+B/lH0b3Q==": true,
      "NAh4c2504BK0cyMet8FIQA==": true,
      "NCwegdxenN6+5IDEKGaWkQ==": true,
      "NGe/xNmuBi0PLZe2it4TaA==": true,
      "NJLrU1xQeOj1RPc9mZLZ2w==": true,
      "NMaXI+8EFoFp3JvcMeDAcg==": true,
      "NMm/2YKfvADIcddNYhEMiA==": true,
      "NNV13x3sgThCNEvGwuygqA==": true,
      "NOViWEGIYj+8ytxXO2tMOA==": true,
      "NY1IJheMjUZ1LlV6CQVUFw==": true,
      "NZfGAkNzXzXhC1F+xDIrEQ==": true,
      "Ne0C0qs53aA+AkhmPAU8Mw==": true,
      "NgCWdfvE5n2yDDht2DCvWA==": true,
      "NgEq/eNjCEyxlw97W1gdiA==": true,
      "Nn1et4lfNWJOqfw9mqFnag==": true,
      "Nyl5BkcV/Ljfl20l/glj7A==": true,
      "O68zdtGBcNWRw9sbZtYk/w==": true,
      "O6BO2VmCaBICy/bE5y0UqA==": true,
      "O7HlBeIh1Cg2bL1zBEXeQA==": true,
      "OD2J7h0GesgwlFI4+S6llA==": true,
      "OHKK/6J6a1O+BFRV+hnAeA==": true,
      "OHyig8sxfyjkX2YEpX7OWw==": true,
      "OJaOfZJFEEQqCPsLo+CFBg==": true,
      "ONSJoJw0ujlY7aLZCWSPdA==": true,
      "OTJuA+TN4eCNtPNwSyk3bQ==": true,
      "OXjES4Z+BoavxK2V0qWboQ==": true,
      "Oi63V5k3OdME1VjmFGkJ+g==": true,
      "OlWFugCoihevdN8MwUPE9A==": true,
      "Owz19cGJXR8ej5o67wOO7g==": true,
      "OxmpWOLcLkHgDd6Mlx5ppg==": true,
      "Ozdii4dZ9D0Aqnsbi8aWNQ==": true,
      "P2OSgBGvYL6LW3gw19U9Qw==": true,
      "P4dNdBvbPDFMxMaILYjvTA==": true,
      "P9B6PABQkDKdeypks9Vu5Q==": true,
      "PEgYJ18CswVOXKxUYYobRg==": true,
      "PHLOHIZs5ZtQsZatB1e/lw==": true,
      "PRIrNTJfdMvmCDanoLj3Rw==": true,
      "PTCyHYivGHm8ZkkLt8tNxQ==": true,
      "PX2eE5H9ctZbZn5QEVPaAQ==": true,
      "PXjbsfrejMkXpPPQJ0+IEA==": true,
      "PZOADWSkyoTmoU4SmsNMwg==": true,
      "Pe3cSW6JFAwViM1k0ZZXuA==": true,
      "Pqh3csT3Z1JMF2VFW1RGbg==": true,
      "Py445zRa4RbFun7o1EKUJA==": true,
      "Pym/2+z7R3LBTPl5promXg==": true,
      "Q/pVHROO32FmvYHXSDTQcw==": true,
      "Q3QZ/K63No9U8t0BcO5Flg==": true,
      "Q8HwMKxFhngEqJHWXOaiQA==": true,
      "Q9+mIRLaWzNq/0s7aSK23g==": true,
      "Q9DY0wT9BqPB6dmdulBA1Q==": true,
      "QA4qUcj7R/4gy6TApNUaDQ==": true,
      "QJpxq0Cpta2/OCcKStbj5A==": true,
      "QJqNIykE30fZZ14xijN2SA==": true,
      "QStKQaX52mcGyLGUfv1t0A==": true,
      "QSya5KRBb/VCLVR7lGs2cw==": true,
      "Qb/x5scyH2r7lMlBz2vX0g==": true,
      "QdRiECKmIfC7bHD5kVbmXQ==": true,
      "QeocQ58uKz9i4xUCmWKEng==": true,
      "QtkxEOk5xaaDYedaV3PPAQ==": true,
      "R0cdIyj9qSfkSfYIgvvZ1w==": true,
      "R1Kky9IhND3uUGGGA1R84w==": true,
      "R7v4b63aCEzdQ7RTiT5rdQ==": true,
      "RAKU8ptiuijSiky+LNAz2A==": true,
      "RBRpHH/xpb6N5ZUmgj1+Lg==": true,
      "RBUUKT8sJ+Bk3PUWv0GAWA==": true,
      "RBs30L0oJgh/EFX+XkTORQ==": true,
      "RD0UtFjJz5WZU+6kkgUitQ==": true,
      "RD9RKWw2/lOg0MeMTh4b+A==": true,
      "RHAPDnr+ECHmRuh903W+4g==": true,
      "RM+8WMJSrvUgNZTqDGiQTg==": true,
      "RMxtxIEFOYSdmgOlj8Z1LQ==": true,
      "RV+u6ZXZsFdyqb8VX9fvig==": true,
      "RZ83w3OawGym0QtLGusRCA==": true,
      "RkW3TSlz3s313y+Lu7LLmw==": true,
      "Ro0l1JCq0Yl5texxbhg67Q==": true,
      "Rp37B9N4QrXFEsq0l1q7Ow==": true,
      "RrZyE7po6iHPKRS3CpzkBg==": true,
      "Ru5YSiEai2672gMc0ENAZA==": true,
      "S/IvTOyfOxUMDKqd0kf+Lg==": true,
      "SC8GVvRhvE4azFhstsheVw==": true,
      "SEGGPvhCb3AZf6AAPTJumg==": true,
      "SFOrEQ864kZ6NKguEd8ScQ==": true,
      "SICbkuxDOqV6jkcKVK5CzA==": true,
      "SKdafQ/UkVe2qgpsRyPwhA==": true,
      "SQrKbTkLqPeAmfcVJb750Q==": true,
      "SfjGczV5xInof46eLlDRJQ==": true,
      "Sq3QMz/lwzA0BXcWSS7ang==": true,
      "SqWKBddjwDmYcZl23LD4Yg==": true,
      "SrT/OjbU5pLgQjozIj/oIg==": true,
      "TRaiB5yEusFf04ErjHPTng==": true,
      "TRygeQCZkjQ1T0Fv8Pk+Nw==": true,
      "TTS+exgRiUpFGuC5OBp22Q==": true,
      "TaEiOCf2KdDtVIBvnpqN+w==": true,
      "Tapt2qF9mHK7ow2DkLG5rQ==": true,
      "TcAI1zPpG6Hb0zzWwHb/KA==": true,
      "Tfuw7RneCfSJBFekytXmzw==": true,
      "TlSyhlQ23Lb0bN2H09c/+Q==": true,
      "TvZnvqPp9pg4psh9MqenVg==": true,
      "TxJnYh2b2DFSrV86guxY1g==": true,
      "Txt0iu9dvS+9hH1vlbu0xw==": true,
      "U+z47u27HyIeDSeu17sk3Q==": true,
      "U199kgHd+pIkmooGEHKI/w==": true,
      "U1QykgwyXkFV0YrEANKCDw==": true,
      "U5TjNeVu7wOOUEocPvOfmg==": true,
      "U94Icf9TQbMJuNCgoSWL/w==": true,
      "U9uO6jdJuJG1EtwHmPUmzw==": true,
      "UFNb7QHQV31A7AwYANAzLQ==": true,
      "ULg0sJtSRkLgYEmCULA0iQ==": true,
      "UQpf7/0PsWj788pRHtJXOg==": true,
      "UTjBTEcqKeHXtKyyGRMz3A==": true,
      "UUqXt/MQvr76KuYWuRVqBg==": true,
      "UahD/HbKZia7MD+8iPwQ8Q==": true,
      "UcA9yIevEqI8Q8V5wfredQ==": true,
      "UcAWFCH8kz37SFoVINmx2g==": true,
      "UcV4yCxUZkxHgSJ3Fl/cSA==": true,
      "UpNWj8aatZbfS2tP0zpBQw==": true,
      "UwL5LjNicWufO2ebM5U+2A==": true,
      "UxKEf8jkmRsikQK8f5R1YQ==": true,
      "V5DHphhgDBNurFJAMa1M/g==": true,
      "V5wKigVpEkT8d10U26qHuA==": true,
      "VGPmSuOaHD4OeED2ot0ElQ==": true,
      "VL1KN+peJCEFdULvifXJLg==": true,
      "VMUbdTR3IlA+itCTvgKYNg==": true,
      "VPeKgF+tAIoA8cl1KXI6kA==": true,
      "VTz381YOC4mGlseVApkxgw==": true,
      "VbihREQjq7S8ioA+aE9aJg==": true,
      "Veos/jqjoBLioM+cmtNw0g==": true,
      "Vm7HS2H/jqhkxG6JGkkdkg==": true,
      "W2hyUTbOkt4Efehen4VjFA==": true,
      "W31VRjcIW9VTTJmYwnRBtw==": true,
      "WT5pA0nxMMryt+xQN/M8TA==": true,
      "WUV7619jdSd2EoIGjetR1w==": true,
      "WWeEopDAQQmdkH7KZ6f5rg==": true,
      "WYghWB0wkmo66gTfPQlx7g==": true,
      "WctdJcqsZ1hEz1j5DztfRA==": true,
      "WdeFoFKVJ0K0ayuL6rXJqg==": true,
      "Wf4Ubd4Csp7yinofLxvX3w==": true,
      "Whhvc9f7HcMtPuAj334efQ==": true,
      "WtcHTYL1YX683tgNGi1hdA==": true,
      "WvBb0wiSctG2CvpNphULKQ==": true,
      "WvhHw+1xIFuUKVgZSmd07A==": true,
      "X4smbfLBz9Ty4Na6osdb2A==": true,
      "XABiGvMJlJ+R1lRxS2U7JQ==": true,
      "XEbzqPMFeW1Sncl7XlOuaw==": true,
      "XMBD/jjpxJQblHfvJ+5Ezg==": true,
      "XS40n8jxcaXxvEzFO7L2xQ==": true,
      "XUxR6wkNyo9UgZmG7gmV4g==": true,
      "XWH1gdxysXenslvoyB6NEQ==": true,
      "Xc/BROEp3oDlPD+CmG30wQ==": true,
      "XeSn7XENv/ItTXFf/lJV3A==": true,
      "Xep64ZVofF5FaShDwGhN+w==": true,
      "XmUjSWZ8wjH1fZ3t0HyMtA==": true,
      "XxxLNpf8NS3G8c6loUt08A==": true,
      "Y2XNhikVZlyLo5MW2nJ10A==": true,
      "Y3ostjP9UiDiwoXaXz1LSQ==": true,
      "Y58tDGhIJpp0irpMjCH9RQ==": true,
      "Y7xStdw1+GURd4uz+qFTxw==": true,
      "YDCl0S3PMB7Nr/BAnoSj4Q==": true,
      "YGAOI0JV1f7+ULm76WaBmA==": true,
      "YS+fpElsTf7dGYbnyqLbvQ==": true,
      "YVRz3x3r8Zly91LMg8hMvQ==": true,
      "YXlAT+D385ytiGMZlFJ+Gw==": true,
      "YXxqw2An3fPu/mgqBnBOkA==": true,
      "YbgYVwy4SpFGU2i/JlLumQ==": true,
      "YgGqP5xHm+k4vYEv6WIGSw==": true,
      "Yo3Xg9I+P2ZPP4ndq2pa4g==": true,
      "Yoj0IyTYTFPDji7iDtKSsg==": true,
      "YsVfWEIiR0ebisfkAm6DAA==": true,
      "YvvGcnf7g1nvrO/MathqIQ==": true,
      "Z/UwOBxCUOCeMuuRcY7Shw==": true,
      "Z/xEOu1zY7tHIgH9i/q2Uw==": true,
      "Z7C8iOFkjKuhfsUW2J7/Kw==": true,
      "ZBEg/BYduwhxLozoZ6QR4g==": true,
      "ZGqPU2v7lHkiFX+DllSq/w==": true,
      "ZORIhoreF72aOk/qjia+Kg==": true,
      "ZSbxPTS37tbDWUVXy4kd+g==": true,
      "ZTm/AEOxpmvS1Lp+Sd0PMQ==": true,
      "ZWoAIA4RG/Rih7JA+I3XAw==": true,
      "ZWrCZsnuMOgGY4L/7NjEQA==": true,
      "ZX8idm4DdvmZclLVr2TyuA==": true,
      "ZaT093lDQA0PFnEJlGRytg==": true,
      "ZaWj/T/pweCkUpK+bKv17g==": true,
      "ZbYlrHXsZhnYERPq58/8wA==": true,
      "Zd+5z8BWH/ekPViI5yEhIw==": true,
      "ZdndTqqMmGjaEF8Vb6UmSg==": true,
      "Zekmbw3FTsY3CMJAKmPEow==": true,
      "ZflGhfmYNS5Pmti9zmDV6g==": true,
      "ZiLvYsVQQN1ib+wsnDEivw==": true,
      "ZqwIC1qn+adLfSyAnGb6lA==": true,
      "ZrohhtFkXeeBwfsWE8+GaA==": true,
      "Zu7iWRCQiRHP94V7JRtbjQ==": true,
      "ZxKJvKlH6VdcLKxX+Vn9cQ==": true,
      "Zyeg/0KLnFKjQNHf4SlLqw==": true,
      "a/EoSzcygZyvcu4a4Y0a1Q==": true,
      "a/cnURuUfHUgfQgSZzvUYg==": true,
      "a9/U2Ta/1TFMFCKEEi9oUg==": true,
      "aHC2tL0x4YO3yaUyEvqupg==": true,
      "aHc6vlwr/MdlDzT7JgZs7g==": true,
      "aJYS36jQxPIPJVVvPX6AUg==": true,
      "aSSz+s8hIEcifurgOiIttw==": true,
      "aSr0UPXCGY6fZxJqwPcvoA==": true,
      "aTmgx5RCVLPaG90/O4j/yg==": true,
      "aVmJBmey0aRWyD3ZfsCJfQ==": true,
      "aXQr9AbGwVuswc3eORyDaw==": true,
      "aYNvnkkliPMIVMmBaBFRkg==": true,
      "ahWoQhP8l7AUiDhJ8FlCXA==": true,
      "aiiB5K3oKGj75zTpD1HbPA==": true,
      "aj6WvdzNyUVtOAtlvBto4w==": true,
      "amsnjoHEBRy3ZDHk8lYU7Q==": true,
      "atnKSe4P6gGDrfTxZONCzg==": true,
      "aw7Uk3Z44i4E8vkfybXLcg==": true,
      "bAsNkGXI1yLSP4avxPoKbQ==": true,
      "bEEAe5n9pm+tVuCg44gO6w==": true,
      "bLrPG2GXWgfTfhS4BhO3Ag==": true,
      "bM2VcNiM4LNqJMFRWnVh+w==": true,
      "bNWKoNLVJOBTcb2rojyzMg==": true,
      "bQhCSC7FsBY7FigWIpb9Jg==": true,
      "bRLN1bjy3YqXl5n3dmc2Fw==": true,
      "bYTBR1orbYRuMkHorq/CkA==": true,
      "bZV2sBlJxReU5QMDZWoJ6g==": true,
      "c4+VAyzcE1US1I8nBN/khA==": true,
      "cRf5j4CZDWfadv+itlnQrw==": true,
      "cYLPQzzkv6v+GLAeGN2TxA==": true,
      "cgFzYtU0Rjpid59cGEuphQ==": true,
      "ciN2L2MEh6hOa9O4EWC6OQ==": true,
      "ckFmrt7GaT6EoANAfWFR1w==": true,
      "ckYMN133EZn9mdJjqh0P8Q==": true,
      "crLSagDOnEkev+wtuaZ3Sw==": true,
      "cuIyuEbZKWtNP5XiswGqIA==": true,
      "cuhAQqH+d8RTXw8Qq1K4vg==": true,
      "cv/zyC3weBquftbXBzrZ1A==": true,
      "d0L0iiMIl1GfQLphildiCw==": true,
      "d1JeE2nr/45lFT8fHr6Tow==": true,
      "d8Rv4VFnDQaoe4hAXrZkVg==": true,
      "dCwcRBGa77IXjWiZH8oXiw==": true,
      "dGgOrR3fhaCGogadjrQCgQ==": true,
      "dH4tD5fcL+/Y8S30NqRbVQ==": true,
      "dIC6keSbOuKdvp9PqbzVpg==": true,
      "dJV+2hVVK5UiJTr7O8W9Xw==": true,
      "dRbqHqDbXMMDuD7U68iySA==": true,
      "daIRq3RjWpczskaWXeOKHw==": true,
      "dcogbr/2fIV9Dn8wC1P1rQ==": true,
      "dgPvi0umbYu+aalD/K0+9w==": true,
      "dpRyae6suLc4iGJfophRsQ==": true,
      "dvH6BA7l/nNyU4dA4JIatw==": true,
      "dvp4otxm+WUBQGLfvtHumQ==": true,
      "dw4y/ppgSlSCYV5ePU0KQw==": true,
      "dwcICoW5k2hUO0+H4aRWkA==": true,
      "dztcBQbLnYcmd1XfUMtyiQ==": true,
      "e5szqX3OQ+iZ0FAo7g+wog==": true,
      "e7bpI8n4eZdR0qxiVBaDgg==": true,
      "e9m1s6Q6fYR5GqV/ZrGEmA==": true,
      "eArtKgHwr+qKJsaF9RNCiA==": true,
      "eCYY9Tte/jQFIaGx582IeA==": true,
      "eJJdgn6Xr9GbyzShlOlh/A==": true,
      "eRqroL/VWE2NqVW/zZqVBQ==": true,
      "ecvYg2QYg9RBva5pTbZfTg==": true,
      "eo9Fl1TeCfJ57nAICE5+yw==": true,
      "ep6dQW5XN8EkzESKtZAtoA==": true,
      "eqXdolk/hCk8HuJklg5Uog==": true,
      "eyUFosxw7ELBf/koW4hcyg==": true,
      "ezduC+N2+jp7m2V1e2P9Iw==": true,
      "f/0ojAsKZtDXDX+Xt60W5A==": true,
      "f18cyGLCMnpX7m7JoC1euQ==": true,
      "f6x1MdKH8TZ35u/F683afw==": true,
      "fNjiFJAbfkychFPEDqzejQ==": true,
      "fQFdvnviacbrXOOM+X8Xvw==": true,
      "fWy4hkpN+Chfipiag+8kFw==": true,
      "fXAlDDV+dR47ocPLzIGEng==": true,
      "fdjt000dymtBtkjrMH3XIQ==": true,
      "g+DAIOjNIuBZ9PK4s8llaQ==": true,
      "g/evMmpTtgyBXUNcwiYNXg==": true,
      "g0B5USe6Dsq8e2xJdZCmig==": true,
      "g9zWcbdIiaZ7dpsSunjcjA==": true,
      "gD8gUuEwwww9FL/OtRvcVQ==": true,
      "gQ/E/pvNkoX8C0S0HawD7w==": true,
      "gUdBC8mPlTcrR49wXHJokQ==": true,
      "gav0oqroNCiCDJlIHIwQMQ==": true,
      "gfu6NhHLMREgV8ULMzkLQg==": true,
      "gkXprT/HhqFuoPxfyY1Eaw==": true,
      "glE6HhNz9vHkZKZuG4KPew==": true,
      "gy4Y8I280wLDL9bEOeP7kg==": true,
      "gzJCHSyllJJbhQW0+eGC/g==": true,
      "hGngZMLFrtbZHGpE3kmrFg==": true,
      "hHtWqyL3UbuC4yWR3Fmtog==": true,
      "hI3G/UZwalvDJKmJV6Oc4Q==": true,
      "hI3H1T2iBUkf7Lh1Md5nLA==": true,
      "hLlSQKM2hcvSzo81GgreNw==": true,
      "hS/uDnPZYA6LKXuPztgqAw==": true,
      "hYJOQbey83fFLkZe2+067A==": true,
      "hcyspDdkFQvn97urYxjChw==": true,
      "hfxW5ERf4JpbgOC5335x1w==": true,
      "hk6CvIJ5OY7vwyohCPyWcw==": true,
      "hoJDMYCDS90ICFDB9FE36Q==": true,
      "hrWKT+uCSZgyaHlZi2xdpw==": true,
      "hwBZ9XfpQd/PKVxecUYCKg==": true,
      "hwTUs02gyAsZ844eKOJ1WA==": true,
      "i3KH7H/l1R4S00ZVpNXVDw==": true,
      "i82QKK2DNPqtR4k9SYo+kA==": true,
      "iB2EI/7JUsM9h2un8t9Xqg==": true,
      "iEFH7kcOpzflWUdRwXJFTg==": true,
      "iG+k7sG/PJFAwvAwHhwveg==": true,
      "iInBEAyNK0NG955DbIxPrg==": true,
      "iVyTDes6qiQPPvPsiSAStg==": true,
      "iq0UvqZj+ofJeXblmXDgYA==": true,
      "iqWv2N73mWb1+g1E5wWSiw==": true,
      "j+9aqdmBT4yLS5CBK0iWnw==": true,
      "j+Oc2Z2+8U8r1dLKlnYbPw==": true,
      "j7PBveAF02keOt3xxIQnPw==": true,
      "jF+h1dThXRDdUDOMzyx5QQ==": true,
      "jI1kzQZf65kAOIyYSVeyaw==": true,
      "jIb26RjziYLFQp5YJ2KxcA==": true,
      "jaUHd6dDI7PMvK7TeSWHYw==": true,
      "jai8i1PPnJy8QkHtOIyBQg==": true,
      "jfeR5CxYN96Tc9JqrWeLXQ==": true,
      "jgOh+kSO0OpUlX4BkZL4Ow==": true,
      "jgP3wx30AppBlDsUOEoIiw==": true,
      "jqKeWiyI+XTol/iJJZWErA==": true,
      "jsFBwHCg21N6corc3bq+EQ==": true,
      "jwDqufqGkDmIdGDqdgyyqQ==": true,
      "k4b4s7v0n5SYh/ORU5oXGA==": true,
      "kBnBckmonXm9Q0g2j3NRCg==": true,
      "kGzcL5PejkUSKlbX9GqjnA==": true,
      "kJTYF5M6RQPMPtUFFCCyQw==": true,
      "kLjbPwASCl7+H8JjD66ivw==": true,
      "kPww8k/LPYwZrSe8tvTopA==": true,
      "kTDuwHTHbeWokwc0VS9YkQ==": true,
      "kXUcq35dCpt4eXFOEeN8sg==": true,
      "ka9VSCXp+2Z1XMknjYZC/g==": true,
      "kcEb0A59I9hWiivH+n+yfw==": true,
      "keXFbfa+H5rGegtA4UMNLg==": true,
      "kfxH09YN5s0A2BJV3OsRZg==": true,
      "kjLbV4PhA/fzTbW19zRfpw==": true,
      "kmkkOBT/cqZ8Xs2yoiifRg==": true,
      "kwaXZ8xbPnl5CrlkadS5IQ==": true,
      "l05X9VozWrPQOCQgD9dFhA==": true,
      "l9qvrJqZzWxYDLvSwBt/xQ==": true,
      "lEpqN8FTuneKDUe2YNRi1g==": true,
      "lKl4PlQEYZcjVJ11oR9rRQ==": true,
      "lKmzmPp1LCxh3iYq59Qu/A==": true,
      "lNwU4pFIKEnKqotEX6a1BQ==": true,
      "lRgb7iG0z3Fa0+oTjWZTiw==": true,
      "lRtaXlOmZci0GrXTamUOQA==": true,
      "lSHDq240lW3wmCG7RTqciA==": true,
      "ldFA0IVOmjinir3TbJNDcA==": true,
      "loQ9oymIkZ+vBRc+cr1Isw==": true,
      "lufFbVMSRieZtTHj3lLNaA==": true,
      "m1I4sZ/n/FlMZDw1eqcdaw==": true,
      "m3WUmni7G/o8TSO/aTKTWw==": true,
      "m59uInPqE7LKCJqPXLd8zw==": true,
      "mBlp0omfwCl3Nk6mUJnG3A==": true,
      "mF/zSrsPmUjw4cLFyDV98w==": true,
      "mMpXdVz++nGFs5NK5IZY6g==": true,
      "mQTM0YYAimBc83nbhJ/aeA==": true,
      "mSdbHOY/dh1d8HVQKVf8pg==": true,
      "mSlQrxsUqJhxG+u4ILBmvg==": true,
      "mdd0gMzdOGvSfrt8LhWeEw==": true,
      "mlXMdEXopnzYP35laD1qaQ==": true,
      "msOs8KzZL4e+huNDzRahDQ==": true,
      "mwJ4V5wwEVRI0JUl37x/tQ==": true,
      "mwiE1uiNCiFemb74OzL+Rg==": true,
      "n/3poPE9E3oHxRqL8Rkmow==": true,
      "n6L15Eku9xVvex3x7EoLNA==": true,
      "n9Ae/Z6FOVdniPATYtIpWQ==": true,
      "nEWLl8qWxO4DALUt3lBBtw==": true,
      "nEbF4ZbOlaS+Fu2ESo2WNQ==": true,
      "nFnd0u31Le69NvWlK15k9Q==": true,
      "nJ+KzBIsiGTU76fqLyD3Ag==": true,
      "nKRLrd7ijKidVQ7x+bA2lA==": true,
      "nPQqTtdNOmMKR9ty4r8Xqw==": true,
      "nQ2koOP4e2uWmxMzkriK7Q==": true,
      "nTvtDqTl5rmhCDYsuHkhTQ==": true,
      "nVj3aqB0JfBLPEmXfmqTjw==": true,
      "nWP8qluhwkpaYBX0G02u0g==": true,
      "nbez3j7PFeDLsYyAws/RpQ==": true,
      "nloKnIqoHUu0Zt3MsDngLQ==": true,
      "npYPW0hweHKPi+O3/kTRqw==": true,
      "ntzoiUkxRG7QrGXfaXi0vQ==": true,
      "nx2y75QzbY4mJ2apoZ/uQw==": true,
      "o/VhpHi8Y0A2ZGasKPxU4Q==": true,
      "o0+safRb+hcyV4n9B9+cuw==": true,
      "o0HPc6XsWMf3dC5c7orNmA==": true,
      "o18KMaGf1cWH921GlocVQw==": true,
      "o1HmO77JFU9l102mTUvpLg==": true,
      "o7wSXEjKxwN+KxpU8cU1NQ==": true,
      "oAjV9PXN1hSpbl+Q0hd+rQ==": true,
      "oBZaer2o1HVlpZIypwMy5g==": true,
      "oCIN6GnX9ZL88Nrk7EWrKQ==": true,
      "oDdyvQ6p+w88X+iSbhpSrA==": true,
      "oITG3srasvFw1vMle3ywng==": true,
      "oT679ho3191lLu0jmNqWOA==": true,
      "oT8S69mgqTAaFIotrVSaxQ==": true,
      "oYJ+5izz6PO6LthRMg7YzA==": true,
      "oakfz7yQyJ5Diu5SFSvQAQ==": true,
      "ohMpfXk72X/jJLwWbUip1Q==": true,
      "ooSpQTNu76X+4YEy5rdtxQ==": true,
      "otAbomD/8oqEgYiyW5Dk2Q==": true,
      "ou9r33i+hVuN02dmSGY/Ug==": true,
      "p0VBd8SbjqMy3MP2nNM40A==": true,
      "p7BAFWTE2cRf4oy8mu4L2g==": true,
      "pA6+lU2369iDI69znoI/rQ==": true,
      "pBAk3ir56kn0dawp+m66PA==": true,
      "pC8Lc5exgD0in+URX1zzzg==": true,
      "pGYK9GcOdIk9T3jrZCsLfA==": true,
      "pHKE9/IzkTg+7o3iyK0OGQ==": true,
      "pJPuCAlHKsCi4r8gqPYl8g==": true,
      "pJeNTA05eK24Xlqcy7qBGw==": true,
      "pMITnDfzSayzPz6hBRWzqQ==": true,
      "pQSOWfb0JmE4iFOIF/K0lQ==": true,
      "pXAWL8t4Z8cbHsybMVCjhg==": true,
      "pZOExfDHCNEKi7mBnuS8gw==": true,
      "pgl5Yx4t6VdDeY97yJEZYQ==": true,
      "ppu8LASBJNWH3T6jZlW7WA==": true,
      "pqdZx9glEcZnAfadEV348A==": true,
      "ptD2CuoD4ryn3wpn0IzWNg==": true,
      "pu1sTAK/Mue867SAAFDkkA==": true,
      "q+zORscRiPhfRMZgOWowaA==": true,
      "qK/WBnZySGRqJPnimS8j8Q==": true,
      "qKux1H6DJ1GcCojS1zaBjw==": true,
      "qMJB81/+Gb7tYn39Rq98gw==": true,
      "qRDXwsn1tsqyvLQF9yg49Q==": true,
      "qRZBCXnMbQPiCOG+K7v/9g==": true,
      "qUcoGygw8/ijMdVwfxlR5w==": true,
      "qajDJ3TO4OpHwQXipiIMiQ==": true,
      "qdxqoakFJA3tcLwPKQwP5w==": true,
      "qf8iZa1yXAaYNx9hWaLq5Q==": true,
      "qlFWpKRMjGyekH3CYeGWEg==": true,
      "qqSJhqDvKogJLgQMWQsvbA==": true,
      "qrERyB/Fseyew3DlSL1wog==": true,
      "qviqZm5hcVUyNafa0LzFbg==": true,
      "qwGjj6C8iOrz5yudxkp06g==": true,
      "r+b7B9dj13qfjnOjLn0z6g==": true,
      "r6qy+iqfN1e6rxmMrAU38g==": true,
      "rCevXSqu6teKo0PK7GqmjA==": true,
      "rGBQXk1LisR02a6HpBKZsw==": true,
      "rflKtvoI+azqRZSGDBJK5g==": true,
      "rpWTUwkqT1Ezu+pe+8ClwA==": true,
      "rsa/dqfX5n2x27/eGKiNzg==": true,
      "rvSK7azbN+lnDjb4nnH4fw==": true,
      "rvWYRYOP3MafHgty0sV0nw==": true,
      "rx193OhjgKlbCmiYq2DgFw==": true,
      "s5M7nIg33FiWAhzR0zdDYg==": true,
      "sDeAk1hpaJAdrldESnDVAw==": true,
      "sXnFGo9u3S0IPQt8w4c6tg==": true,
      "sYOXhMILEFK4kWp4Gk9QUQ==": true,
      "saQku/Vp1L7ZixbMLcQUiw==": true,
      "sasE+nu2lmOPdRdI1b8Y6g==": true,
      "sckXXvkTUWHdoCxlagBgaA==": true,
      "sdXYVVYZZa+N1FyDYSPTaQ==": true,
      "sh4HqaRBGXVeXro1paLQsQ==": true,
      "si6tSA1iJ6SLFOiA2WgDtQ==": true,
      "slbXuhie0iyuuPbICr91aA==": true,
      "sln7kCSeB6mNq0Q69afzvA==": true,
      "stDYgeQ3f9ah1o+KPRotGw==": true,
      "subPqhhdLZMc1ImP+JUBzA==": true,
      "sulMNE9AV4RumePpU+HRyg==": true,
      "svjLTCJQOj4o4bXGvenirA==": true,
      "tJ2jVxHyZ+lkBEJLPhUBBw==": true,
      "tPHfnTbDvRW8nu6Zh2FMCQ==": true,
      "tZvirLpkqDf6DYJinp2XgQ==": true,
      "tcxXPwix8sVcbXEEH5P7Iw==": true,
      "tj/ltQDxyR+6NP77/GZQug==": true,
      "tla2kC+6p1Esu9be0LH4eQ==": true,
      "u4iEbbqIl78CxBN0flcs6Q==": true,
      "u4yoky9Bujehnjz4yC750g==": true,
      "u7C5/Lr7n3GceV6CDglz3w==": true,
      "u8mcrfZPv7G1jOic2zGwMQ==": true,
      "u9DvHBV5k80LtDM9DRBNog==": true,
      "uBEOpqXc19v5ICM0umfi7w==": true,
      "uGQm1XJf35mplQ1UiKdDHw==": true,
      "uH8E4Wllbhu1G16wgmStTw==": true,
      "uQQ4tziuEgp1Cm10VYRaaQ==": true,
      "uSkDiVWp1ot5ZuMdzLxAUw==": true,
      "uUyRFu4SLC4pG2GiiXu1IQ==": true,
      "uXPf2ieSPCCrtTATmLF0PQ==": true,
      "uZzjkBOLR0nvHTZa/pfWQA==": true,
      "ueLl7E3ZvYk7afXpPJUOvw==": true,
      "uf6eQzXcpVxJqU3HUqUQyg==": true,
      "uhn2XJDYvDsgtsi+oTnPsw==": true,
      "ul4CCRbpg78zQMkYtzUdUw==": true,
      "umTNdFy6D/jKUVWsuXCc7A==": true,
      "uoEb+mPlv337I3dhgDxpIA==": true,
      "v2F3KgXj1lq138tdl3qctg==": true,
      "v7GlayVc6U2p39i+EMXwMg==": true,
      "vBVll1DarA3iTcMkt71pLw==": true,
      "vC89pij9iIOpRDCSx5gNAw==": true,
      "vEoWx2KibcWF7pmc67uw8Q==": true,
      "vI7zveSwB4mrQ6FrCishVQ==": true,
      "vYE5s/BgjsHpjIdTKiK3Xg==": true,
      "vc0gR5Y6u51bX6dILmBY4g==": true,
      "vuFjKSqd0Q8afEIzrw9xyw==": true,
      "vvifuFr6vWPOtBmz3sj3EQ==": true,
      "w1bRF6SppxCDRj6if4snXw==": true,
      "w3YeGG/bc4tS0B3ZLFd+1w==": true,
      "w6EN8dYW/n5FiDZgw0CAuw==": true,
      "w9xRYl8B9sCsi6rsF1dtyw==": true,
      "wA8ututCLemgJUx83+i5Lg==": true,
      "wAJq2OY38aUOzFzqRYkBng==": true,
      "wLaLzfI/4HdKWGUXTZ9X4w==": true,
      "wOm/msYPtOeS0e3/M1TapA==": true,
      "wPweiXw/kgU12JzWESkR3A==": true,
      "wQWLli37v98+Rz7FphHWBw==": true,
      "wXKmD17uJ666gCUaTpNVCQ==": true,
      "wbVr9jhZqyDGMyDTaPJ06w==": true,
      "wdm0yNZt/Eh00aJhzGm6eQ==": true,
      "wj6JG8z/PMbtbBljWmG6hg==": true,
      "wkgTMSV0HEEi6+69BoU8oQ==": true,
      "wqZGR3skECegnrYglwcvPQ==": true,
      "wrQF4DkAXk7fstPuYlPsTg==": true,
      "ww2HoWt6vk5hBeC4LRvQ7g==": true,
      "x1dc7KEsKnoSxCWCyRn9cg==": true,
      "xCBAn2YBiteKf4O57Foh0A==": true,
      "xFfXtn3mchP4/WzWp4SSXQ==": true,
      "xIyxIovCgJlhjtLoLV5z5A==": true,
      "xSKvsva0q5SHogbZGoSsGQ==": true,
      "xSuApRC/CHma+Ic1yJ965w==": true,
      "xaK2QWvwHSwu2y4GMRZsCw==": true,
      "xaql6QZ2ZUWGP1iovMqf2A==": true,
      "xdpMcKK6kut+F1o0NCEA/g==": true,
      "xgstVNYxCnjwwgg6nAJvXw==": true,
      "xjm6R3p/cE11Ue9hzfD4zw==": true,
      "xrjuTV4hbjaIGB5ktD/EBA==": true,
      "xvaK/Qcf8QotzIoJMB9LKQ==": true,
      "xzUMCGlsQMteZ+ge8vasGg==": true,
      "y2YJsPUyxNKvjj/qJ0q/Tg==": true,
      "y47H0IT3hMKxRbiLLur4lQ==": true,
      "y7CJ8oZ9pTTITn0szaG+9A==": true,
      "y9jnEDJHOu4QT0ZUQyG2Wg==": true,
      "yBIba666n5UCs+KjkoTHoA==": true,
      "yJO0K79+4b+pun+olOp3WA==": true,
      "yL80Jbw0OYWRyzZ5ooYWhA==": true,
      "yTFP/wsUFML15znDjy1KLQ==": true,
      "yTlF1vIrD/kul9TzC7OR6A==": true,
      "ycR4XzcFao+gEwFI+RP3nA==": true,
      "ygflsXR9vEgwEBiBNC5JcQ==": true,
      "yro0hliQkRK1VyX0Kgv1nQ==": true,
      "ytpk5nNF+Npkgd8rRJnfwQ==": true,
      "ytwh1ByFvtDaanPe9NDuFQ==": true,
      "yzVHhDkeTy0qS8KuR7ywHw==": true,
      "yzn3ANOUcjyQ3OBwZe+xSA==": true,
      "z0tNdNxIhFyl5yH/dEf/Vg==": true,
      "z1DAm8NuyGOM+OdxLUXS1w==": true,
      "z3VNwHGZnb+AwITaVsbeTg==": true,
      "zDyKoiZVZAQQ2mSeXVXjQg==": true,
      "zGTXxYyxbsA+gAnZz/m4LQ==": true,
      "zMRA0OVKYM3+RSqbNQpylg==": true,
      "zO6r3nXTYNiG//Zi1H+Kjg==": true,
      "zUBbYw2yw4S1R8Ryg06Nzg==": true,
      "zXOGZsWNKmdkHmW2mLqTOw==": true,
      "zdvddiJd6osbLSsrJsTdJw==": true,
      "zfhitE5ks7gqFFAH5JfnQA==": true,
      "zmTECOwMGNDK118H2ojKEA==": true,
      "zmVRjc2oZ7ITh5fez3g0dw==": true,
      "ztt/BasKrpcTHkJ2z2x/+A==": true
    }
  },
  "countryColors": [
    {
      "name_us": "EU Green",
      "name_nl": "EU Groen",
      "code": "code_green",
      "color": "green",
      "result_on_valid_code": "pass",
      "is_EU": true,
      "is_colour_code": true
    },
    {
      "name_us": "EU Yellow",
      "name_nl": "EU Geel",
      "code": "code_yellow",
      "color": "yellow",
      "result_on_valid_code": "pass",
      "is_EU": true,
      "is_colour_code": true
    },
    {
      "name_us": "EU Orange very high risk VOC",
      "name_nl": "EU Oranje zeer hoog risico VOC",
      "code": "code_orange_very_high_risk",
      "color": "orange_very_high_risk",
      "result_on_valid_code": "pass",
      "is_EU": true,
      "is_colour_code": true
    },
    {
      "name_us": "Non-EU Yellow",
      "name_nl": "Niet-EU Geel",
      "code": "code_yellow_neu",
      "color": "yellow",
      "result_on_valid_code": "pass",
      "is_EU": false,
      "is_colour_code": true
    },
    {
      "name_us": "Non-EU Orange high risk",
      "name_nl": "Niet-EU Oranje hoog risico",
      "code": "code_orange_neu",
      "color": "orange",
      "result_on_valid_code": "pass",
      "is_EU": false,
      "is_colour_code": true
    },
    {
      "name_us": "Non-EU Orange very high risk",
      "name_nl": "Niet-EU Oranje zeer hoog risico",
      "code": "code_orange_high_incidence_neu",
      "color": "orange_high_incidence",
      "result_on_valid_code": "pass",
      "is_EU": false,
      "is_colour_code": true
    },
    {
      "name_us": "Non-EU Orange very high risk VOC",
      "name_nl": "Niet-EU Oranje zeer hoog risico VOC",
      "code": "code_orange_very_high_risk_neu",
      "color": "orange_very_high_risk",
      "result_on_valid_code": "pass",
      "is_EU": false,
      "is_colour_code": true
    },
    {
      "name_us": "No rules",
      "name_nl": "Geen regels",
      "code": "code_red",
      "color": "red",
      "result_on_valid_code": "inconclusive",
      "is_EU": true,
      "is_colour_code": true
    },
    {
      "name_us": "Afghanistan",
      "name_nl": "Afghanistan",
      "code": "AF",
      "color": "orange_high_incidence",
      "result_on_valid_code": "pass",
      "is_EU": false,
      "is_colour_code": false
    },
    {
      "name_us": "Aland Islands",
      "name_nl": "Aland",
      "code": "AX",
      "color": "orange",
      "result_on_valid_code": "pass",
      "is_EU": false,
      "is_colour_code": false
    },
    {
      "name_us": "Albania",
      "name_nl": "Albanie",
      "code": "AL",
      "color": "orange",
      "result_on_valid_code": "pass",
      "is_EU": false,
      "is_colour_code": false
    },
    {
      "name_us": "Algeria",
      "name_nl": "Algerije",
      "code": "DZ",
      "color": "orange",
      "result_on_valid_code": "pass",
      "is_EU": false,
      "is_colour_code": false
    },
    {
      "name_us": "American Samoa",
      "name_nl": "Amerikaans-Samoa",
      "code": "AS",
      "color": "orange",
      "result_on_valid_code": "pass",
      "is_EU": false,
      "is_colour_code": false
    },
    {
      "name_us": "Andorra",
      "name_nl": "Andorra",
      "code": "AD",
      "color": "orange",
      "result_on_valid_code": "pass",
      "is_EU": false,
      "is_colour_code": false
    },
    {
      "name_us": "Angola",
      "name_nl": "Angola",
      "code": "AO",
      "color": "orange",
      "result_on_valid_code": "pass",
      "is_EU": false,
      "is_colour_code": false
    },
    {
      "name_us": "Anguilla",
      "name_nl": "Anguilla",
      "code": "AI",
      "color": "orange_high_incidence",
      "result_on_valid_code": "pass",
      "is_EU": false,
      "is_colour_code": false
    },
    {
      "name_us": "Antarctica",
      "name_nl": "Antarctica",
      "code": "AQ",
      "color": "orange",
      "result_on_valid_code": "pass",
      "is_EU": false,
      "is_colour_code": false
    },
    {
      "name_us": "Antigua and Barbuda",
      "name_nl": "Antigua en Barbuda",
      "code": "AG",
      "color": "orange",
      "result_on_valid_code": "pass",
      "is_EU": false,
      "is_colour_code": false
    },
    {
      "name_us": "Argentina",
      "name_nl": "Argentinie",
      "code": "AR",
      "color": "orange_high_incidence",
      "result_on_valid_code": "pass",
      "is_EU": false,
      "is_colour_code": false
    },
    {
      "name_us": "Armenia",
      "name_nl": "Armenie",
      "code": "AM",
      "color": "orange",
      "result_on_valid_code": "pass",
      "is_EU": false,
      "is_colour_code": false
    },
    {
      "name_us": "Aruba",
      "name_nl": "Aruba",
      "code": "AW",
      "color": "yellow",
      "result_on_valid_code": "pass",
      "is_EU": true,
      "is_colour_code": false
    },
    {
      "name_us": "Australia",
      "name_nl": "Australie",
      "code": "AU",
      "color": "orange_high_incidence",
      "result_on_valid_code": "pass",
      "is_EU": false,
      "is_colour_code": false
    },
    {
      "name_us": "Austria",
      "name_nl": "Oostenrijk",
      "code": "AT",
      "color": "yellow",
      "result_on_valid_code": "pass",
      "is_EU": true,
      "is_colour_code": false
    },
    {
      "name_us": "Azerbeidzjan",
      "name_nl": "Azerbeidzjan",
      "code": "AZ",
      "color": "orange",
      "result_on_valid_code": "pass",
      "is_EU": false,
      "is_colour_code": false
    },
    {
      "name_us": "Bahamas",
      "name_nl": "Bahama\u0027s",
      "code": "BS",
      "color": "orange",
      "result_on_valid_code": "pass",
      "is_EU": false,
      "is_colour_code": false
    },
    {
      "name_us": "Bahrain",
      "name_nl": "Bahrein",
      "code": "BH",
      "color": "yellow",
      "result_on_valid_code": "pass",
      "is_EU": false,
      "is_colour_code": false
    },
    {
      "name_us": "Bangladesh",
      "name_nl": "Bangladesh",
      "code": "BD",
      "color": "orange",
      "result_on_valid_code": "pass",
      "is_EU": false,
      "is_colour_code": false
    },
    {
      "name_us": "Barbados",
      "name_nl": "Barbados",
      "code": "BB",
      "color": "orange_high_incidence",
      "result_on_valid_code": "pass",
      "is_EU": false,
      "is_colour_code": false
    },
    {
      "name_us": "Belarus",
      "name_nl": "Wit-Rusland",
      "code": "BY",
      "color": "orange",
      "result_on_valid_code": "pass",
      "is_EU": false,
      "is_colour_code": false
    },
    {
      "name_us": "Belgium",
      "name_nl": "Belgie",
      "code": "BE",
      "color": "yellow",
      "result_on_valid_code": "pass",
      "is_EU": true,
      "is_colour_code": false
    },
    {
      "name_us": "Belize",
      "name_nl": "Belize",
      "code": "BZ",
      "color": "orange_high_incidence",
      "result_on_valid_code": "pass",
      "is_EU": false,
      "is_colour_code": false
    },
    {
      "name_us": "Benin",
      "name_nl": "Benin",
      "code": "BJ",
      "color": "orange",
      "result_on_valid_code": "pass",
      "is_EU": false,
      "is_colour_code": false
    },
    {
      "name_us": "Bermuda",
      "name_nl": "Bermuda",
      "code": "BM",
      "color": "orange",
      "result_on_valid_code": "pass",
      "is_EU": false,
      "is_colour_code": false
    },
    {
      "name_us": "Bhutan",
      "name_nl": "Bhutan",
      "code": "BT",
      "color": "orange",
      "result_on_valid_code": "pass",
      "is_EU": false,
      "is_colour_code": false
    },
    {
      "name_us": "Bolivia (Plurinational State of)",
      "name_nl": "Bolivia",
      "code": "BO",
      "color": "orange",
      "result_on_valid_code": "pass",
      "is_EU": false,
      "is_colour_code": false
    },
    {
      "name_us": "Bonaire",
      "name_nl": "Bonaire",
      "code": "BQ-1",
      "color": "yellow",
      "result_on_valid_code": "pass",
      "is_EU": true,
      "is_colour_code": false
    },
    {
      "name_us": "Bosnia and Herzegovina",
      "name_nl": "Bosnie Herzegovina",
      "code": "BA",
      "color": "orange",
      "result_on_valid_code": "pass",
      "is_EU": false,
      "is_colour_code": false
    },
    {
      "name_us": "Botswana",
      "name_nl": "Botswana",
      "code": "BW",
      "color": "orange_high_incidence",
      "result_on_valid_code": "pass",
      "is_EU": false,
      "is_colour_code": false
    },
    {
      "name_us": "Bouvet Island",
      "name_nl": "Bouvet",
      "code": "BV",
      "color": "orange",
      "result_on_valid_code": "pass",
      "is_EU": false,
      "is_colour_code": false
    },
    {
      "name_us": "Brazil",
      "name_nl": "Brazilie",
      "code": "BR",
      "color": "orange",
      "result_on_valid_code": "pass",
      "is_EU": false,
      "is_colour_code": false
    },
    {
      "name_us": "British Indian Ocean Territory",
      "name_nl": "Brits Indische Oceaanterritorium",
      "code": "IO",
      "color": "orange",
      "result_on_valid_code": "pass",
      "is_EU": false,
      "is_colour_code": false
    },
    {
      "name_us": "Brunei Darussalam",
      "name_nl": "Brunei",
      "code": "BN",
      "color": "orange",
      "result_on_valid_code": "pass",
      "is_EU": false,
      "is_colour_code": false
    },
    {
      "name_us": "Bulgaria",
      "name_nl": "Bulgarije",
      "code": "BG",
      "color": "yellow",
      "result_on_valid_code": "pass",
      "is_EU": true,
      "is_colour_code": false
    },
    {
      "name_us": "Burkina Faso",
      "name_nl": "Burkina Faso",
      "code": "BF",
      "color": "orange",
      "result_on_valid_code": "pass",
      "is_EU": false,
      "is_colour_code": false
    },
    {
      "name_us": "Burundi",
      "name_nl": "Burundi",
      "code": "BI",
      "color": "orange",
      "result_on_valid_code": "pass",
      "is_EU": false,
      "is_colour_code": false
    },
    {
      "name_us": "Cabo Verde",
      "name_nl": "Kaapverdie",
      "code": "CV",
      "color": "orange_high_incidence",
      "result_on_valid_code": "pass",
      "is_EU": false,
      "is_colour_code": false
    },
    {
      "name_us": "Cambodia",
      "name_nl": "Cambodja",
      "code": "KH",
      "color": "orange",
      "result_on_valid_code": "pass",
      "is_EU": false,
      "is_colour_code": false
    },
    {
      "name_us": "Cameroon",
      "name_nl": "Kameroen",
      "code": "CM",
      "color": "orange",
      "result_on_valid_code": "pass",
      "is_EU": false,
      "is_colour_code": false
    },
    {
      "name_us": "Canada",
      "name_nl": "Canada",
      "code": "CA",
      "color": "orange_high_incidence",
      "result_on_valid_code": "pass",
      "is_EU": false,
      "is_colour_code": false
    },
    {
      "name_us": "Cayman Islands",
      "name_nl": "Kaaimaneilanden",
      "code": "KY",
      "color": "orange_high_incidence",
      "result_on_valid_code": "pass",
      "is_EU": false,
      "is_colour_code": false
    },
    {
      "name_us": "Central African Republic",
      "name_nl": "Centraal-Afrikaanse Republiek",
      "code": "CF",
      "color": "orange",
      "result_on_valid_code": "pass",
      "is_EU": false,
      "is_colour_code": false
    },
    {
      "name_us": "Chad",
      "name_nl": "Tsjaad",
      "code": "TD",
      "color": "orange",
      "result_on_valid_code": "pass",
      "is_EU": false,
      "is_colour_code": false
    },
    {
      "name_us": "Chile",
      "name_nl": "Chili",
      "code": "CL",
      "color": "yellow",
      "result_on_valid_code": "pass",
      "is_EU": false,
      "is_colour_code": false
    },
    {
      "name_us": "China",
      "name_nl": "China",
      "code": "CN",
      "color": "orange",
      "result_on_valid_code": "pass",
      "is_EU": false,
      "is_colour_code": false
    },
    {
      "name_us": "Christmas Island",
      "name_nl": "Christmaseiland",
      "code": "CX",
      "color": "orange",
      "result_on_valid_code": "pass",
      "is_EU": false,
      "is_colour_code": false
    },
    {
      "name_us": "Cocos (Keeling) Islands",
      "name_nl": "Cocoseilanden",
      "code": "CC",
      "color": "orange",
      "result_on_valid_code": "pass",
      "is_EU": false,
      "is_colour_code": false
    },
    {
      "name_us": "Colombia",
      "name_nl": "Colombia",
      "code": "CO",
      "color": "yellow",
      "result_on_valid_code": "pass",
      "is_EU": false,
      "is_colour_code": false
    },
    {
      "name_us": "Comoros",
      "name_nl": "Comoren",
      "code": "KM",
      "color": "orange",
      "result_on_valid_code": "pass",
      "is_EU": false,
      "is_colour_code": false
    },
    {
      "name_us": "Congo",
      "name_nl": "Congo-Brazzaville",
      "code": "CG",
      "color": "orange",
      "result_on_valid_code": "pass",
      "is_EU": false,
      "is_colour_code": false
    },
    {
      "name_us": "Congo,  Democratic Republic of the",
      "name_nl": "Congo-Kinshasa",
      "code": "CD",
      "color": "orange",
      "result_on_valid_code": "pass",
      "is_EU": false,
      "is_colour_code": false
    },
    {
      "name_us": "Cook Islands",
      "name_nl": "Cookeilanden",
      "code": "CK",
      "color": "orange",
      "result_on_valid_code": "pass",
      "is_EU": false,
      "is_colour_code": false
    },
    {
      "name_us": "Costa Rica",
      "name_nl": "Costa Rica",
      "code": "CR",
      "color": "orange",
      "result_on_valid_code": "pass",
      "is_EU": false,
      "is_colour_code": false
    },
    {
      "name_us": "Cote d\u0027Ivoire",
      "name_nl": "Ivoorkust",
      "code": "CI",
      "color": "orange",
      "result_on_valid_code": "pass",
      "is_EU": false,
      "is_colour_code": false
    },
    {
      "name_us": "Croatia",
      "name_nl": "Kroatie",
      "code": "HR",
      "color": "yellow",
      "result_on_valid_code": "pass",
      "is_EU": true,
      "is_colour_code": false
    },
    {
      "name_us": "Cuba",
      "name_nl": "Cuba",
      "code": "CU",
      "color": "orange",
      "result_on_valid_code": "pass",
      "is_EU": false,
      "is_colour_code": false
    },
    {
      "name_us": "Curacao",
      "name_nl": "Curacao",
      "code": "CW",
      "color": "yellow",
      "result_on_valid_code": "pass",
      "is_EU": true,
      "is_colour_code": false
    },
    {
      "name_us": "Cyprus",
      "name_nl": "Cyprus",
      "code": "CY",
      "color": "yellow",
      "result_on_valid_code": "pass",
      "is_EU": true,
      "is_colour_code": false
    },
    {
      "name_us": "Czechia",
      "name_nl": "Tsjechie",
      "code": "CZ",
      "color": "yellow",
      "result_on_valid_code": "pass",
      "is_EU": true,
      "is_colour_code": false
    },
    {
      "name_us": "Denmark",
      "name_nl": "Denemarken",
      "code": "DK",
      "color": "yellow",
      "result_on_valid_code": "pass",
      "is_EU": true,
      "is_colour_code": false
    },
    {
      "name_us": "Djibouti",
      "name_nl": "Djibouti",
      "code": "DJ",
      "color": "orange",
      "result_on_valid_code": "pass",
      "is_EU": false,
      "is_colour_code": false
    },
    {
      "name_us": "Dominica",
      "name_nl": "Dominica",
      "code": "DM",
      "color": "orange_high_incidence",
      "result_on_valid_code": "pass",
      "is_EU": false,
      "is_colour_code": false
    },
    {
      "name_us": "Dominican Republic",
      "name_nl": "Dominicaanse Republiek",
      "code": "DO",
      "color": "orange",
      "result_on_valid_code": "pass",
      "is_EU": false,
      "is_colour_code": false
    },
    {
      "name_us": "Ecuador",
      "name_nl": "Ecuador",
      "code": "EC",
      "color": "orange",
      "result_on_valid_code": "pass",
      "is_EU": false,
      "is_colour_code": false
    },
    {
      "name_us": "Egypt",
      "name_nl": "Egypte",
      "code": "EG",
      "color": "orange",
      "result_on_valid_code": "pass",
      "is_EU": false,
      "is_colour_code": false
    },
    {
      "name_us": "El Salvador",
      "name_nl": "El Salvador",
      "code": "SV",
      "color": "orange",
      "result_on_valid_code": "pass",
      "is_EU": false,
      "is_colour_code": false
    },
    {
      "name_us": "Equatorial Guinea",
      "name_nl": "Equatoriaal-Guinea",
      "code": "GQ",
      "color": "orange",
      "result_on_valid_code": "pass",
      "is_EU": false,
      "is_colour_code": false
    },
    {
      "name_us": "Eritrea",
      "name_nl": "Eritrea",
      "code": "ER",
      "color": "orange",
      "result_on_valid_code": "pass",
      "is_EU": false,
      "is_colour_code": false
    },
    {
      "name_us": "Estonia",
      "name_nl": "Estland",
      "code": "EE",
      "color": "green",
      "result_on_valid_code": "pass",
      "is_EU": true,
      "is_colour_code": false
    },
    {
      "name_us": "Eswatini",
      "name_nl": "Swaziland",
      "code": "SZ",
      "color": "orange_high_incidence",
      "result_on_valid_code": "pass",
      "is_EU": false,
      "is_colour_code": false
    },
    {
      "name_us": "Ethiopia",
      "name_nl": "Ethiopie",
      "code": "ET",
      "color": "orange",
      "result_on_valid_code": "pass",
      "is_EU": false,
      "is_colour_code": false
    },
    {
      "name_us": "Falkland Islands (Malvinas)",
      "name_nl": "Falklandeilanden",
      "code": "FK",
      "color": "orange",
      "result_on_valid_code": "pass",
      "is_EU": false,
      "is_colour_code": false
    },
    {
      "name_us": "Faroe Islands",
      "name_nl": "Faeroer",
      "code": "FO",
      "color": "yellow",
      "result_on_valid_code": "pass",
      "is_EU": false,
      "is_colour_code": false
    },
    {
      "name_us": "Fiji",
      "name_nl": "Fiji",
      "code": "FJ",
      "color": "orange",
      "result_on_valid_code": "pass",
      "is_EU": false,
      "is_colour_code": false
    },
    {
      "name_us": "Finland",
      "name_nl": "Finland",
      "code": "FI",
      "color": "yellow",
      "result_on_valid_code": "pass",
      "is_EU": true,
      "is_colour_code": false
    },
    {
      "name_us": "France",
      "name_nl": "Frankrijk",
      "code": "FR",
      "color": "yellow",
      "result_on_valid_code": "pass",
      "is_EU": true,
      "is_colour_code": false
    },
    {
      "name_us": "French Guiana",
      "name_nl": "Frans-Guyana",
      "code": "GF",
      "color": "orange_high_incidence",
      "result_on_valid_code": "pass",
      "is_EU": true,
      "is_colour_code": false
    },
    {
      "name_us": "French Polynesia",
      "name_nl": "Frans-Polynesie",
      "code": "PF",
      "color": "orange",
      "result_on_valid_code": "pass",
      "is_EU": false,
      "is_colour_code": false
    },
    {
      "name_us": "French Southern Territories",
      "name_nl": "Franse Zuidelijke Gebieden",
      "code": "TF",
      "color": "orange",
      "result_on_valid_code": "pass",
      "is_EU": false,
      "is_colour_code": false
    },
    {
      "name_us": "Gabon",
      "name_nl": "Gabon",
      "code": "GA",
      "color": "orange",
      "result_on_valid_code": "pass",
      "is_EU": false,
      "is_colour_code": false
    },
    {
      "name_us": "Gambia",
      "name_nl": "Gambia",
      "code": "GM",
      "color": "orange",
      "result_on_valid_code": "pass",
      "is_EU": false,
      "is_colour_code": false
    },
    {
      "name_us": "Georgia",
      "name_nl": "Georgie",
      "code": "GE",
      "color": "orange_high_incidence",
      "result_on_valid_code": "pass",
      "is_EU": false,
      "is_colour_code": false
    },
    {
      "name_us": "Germany",
      "name_nl": "Duitsland",
      "code": "DE",
      "color": "yellow",
      "result_on_valid_code": "pass",
      "is_EU": true,
      "is_colour_code": false
    },
    {
      "name_us": "Ghana",
      "name_nl": "Ghana",
      "code": "GH",
      "color": "orange",
      "result_on_valid_code": "pass",
      "is_EU": false,
      "is_colour_code": false
    },
    {
      "name_us": "Gibraltar",
      "name_nl": "Gibraltar",
      "code": "GI",
      "color": "orange",
      "result_on_valid_code": "pass",
      "is_EU": false,
      "is_colour_code": false
    },
    {
      "name_us": "Greece",
      "name_nl": "Griekenland",
      "code": "GR",
      "color": "yellow",
      "result_on_valid_code": "pass",
      "is_EU": true,
      "is_colour_code": false
    },
    {
      "name_us": "Greenland",
      "name_nl": "Groenland",
      "code": "GL",
      "color": "yellow",
      "result_on_valid_code": "pass",
      "is_EU": false,
      "is_colour_code": false
    },
    {
      "name_us": "Grenada",
      "name_nl": "Grenada",
      "code": "GD",
      "color": "orange",
      "result_on_valid_code": "pass",
      "is_EU": false,
      "is_colour_code": false
    },
    {
      "name_us": "Guadeloupe",
      "name_nl": "Guadeloupe",
      "code": "GP",
      "color": "orange_high_incidence",
      "result_on_valid_code": "pass",
      "is_EU": true,
      "is_colour_code": false
    },
    {
      "name_us": "Guam",
      "name_nl": "Guam",
      "code": "GU",
      "color": "orange",
      "result_on_valid_code": "pass",
      "is_EU": false,
      "is_colour_code": false
    },
    {
      "name_us": "Guatemala",
      "name_nl": "Guatemala",
      "code": "GT",
      "color": "orange",
      "result_on_valid_code": "pass",
      "is_EU": false,
      "is_colour_code": false
    },
    {
      "name_us": "Guernsey",
      "name_nl": "Guernsey",
      "code": "GG",
      "color": "orange",
      "result_on_valid_code": "pass",
      "is_EU": false,
      "is_colour_code": false
    },
    {
      "name_us": "Guinea",
      "name_nl": "Guinee",
      "code": "GN",
      "color": "orange",
      "result_on_valid_code": "pass",
      "is_EU": false,
      "is_colour_code": false
    },
    {
      "name_us": "Guinea-Bissau",
      "name_nl": "Guinee-Bissau",
      "code": "GW",
      "color": "orange",
      "result_on_valid_code": "pass",
      "is_EU": false,
      "is_colour_code": false
    },
    {
      "name_us": "Guyana",
      "name_nl": "Guyana",
      "code": "GY",
      "color": "orange",
      "result_on_valid_code": "pass",
      "is_EU": false,
      "is_colour_code": false
    },
    {
      "name_us": "Haiti",
      "name_nl": "Haiti",
      "code": "HT",
      "color": "orange_high_incidence",
      "result_on_valid_code": "pass",
      "is_EU": false,
      "is_colour_code": false
    },
    {
      "name_us": "Heard Island and McDonald Islands",
      "name_nl": "Heard en McDonaldeilanden",
      "code": "HM",
      "color": "orange",
      "result_on_valid_code": "pass",
      "is_EU": false,
      "is_colour_code": false
    },
    {
      "name_us": "Honduras",
      "name_nl": "Honduras",
      "code": "HN",
      "color": "orange",
      "result_on_valid_code": "pass",
      "is_EU": false,
      "is_colour_code": false
    },
    {
      "name_us": "Hong Kong",
      "name_nl": "Hongkong",
      "code": "HK",
      "color": "yellow",
      "result_on_valid_code": "pass",
      "is_EU": false,
      "is_colour_code": false
    },
    {
      "name_us": "Hungary",
      "name_nl": "Hongarije",
      "code": "HU",
      "color": "yellow",
      "result_on_valid_code": "pass",
      "is_EU": true,
      "is_colour_code": false
    },
    {
      "name_us": "Iceland",
      "name_nl": "IJsland",
      "code": "IS",
      "color": "yellow",
      "result_on_valid_code": "pass",
      "is_EU": true,
      "is_colour_code": false
    },
    {
      "name_us": "India",
      "name_nl": "India",
      "code": "IN",
      "color": "orange",
      "result_on_valid_code": "pass",
      "is_EU": false,
      "is_colour_code": false
    },
    {
      "name_us": "Indonesia",
      "name_nl": "Indonesie",
      "code": "ID",
      "color": "orange_high_incidence",
      "result_on_valid_code": "pass",
      "is_EU": false,
      "is_colour_code": false
    },
    {
      "name_us": "Iran (Islamic Republic of)",
      "name_nl": "Iran",
      "code": "IR",
      "color": "orange",
      "result_on_valid_code": "pass",
      "is_EU": false,
      "is_colour_code": false
    },
    {
      "name_us": "Iraq",
      "name_nl": "Irak",
      "code": "IQ",
      "color": "orange",
      "result_on_valid_code": "pass",
      "is_EU": false,
      "is_colour_code": false
    },
    {
      "name_us": "Ireland",
      "name_nl": "Ierland",
      "code": "IE",
      "color": "yellow",
      "result_on_valid_code": "pass",
      "is_EU": true,
      "is_colour_code": false
    },
    {
      "name_us": "Isle of Man",
      "name_nl": "Man",
      "code": "IM",
      "color": "orange",
      "result_on_valid_code": "pass",
      "is_EU": false,
      "is_colour_code": false
    },
    {
      "name_us": "Israel",
      "name_nl": "Israel",
      "code": "IL",
      "color": "orange_high_incidence",
      "result_on_valid_code": "pass",
      "is_EU": false,
      "is_colour_code": false
    },
    {
      "name_us": "Italy",
      "name_nl": "Italie",
      "code": "IT",
      "color": "yellow",
      "result_on_valid_code": "pass",
      "is_EU": true,
      "is_colour_code": false
    },
    {
      "name_us": "Jamaica",
      "name_nl": "Jamaica",
      "code": "JM",
      "color": "orange",
      "result_on_valid_code": "pass",
      "is_EU": false,
      "is_colour_code": false
    },
    {
      "name_us": "Japan",
      "name_nl": "Japan",
      "code": "JP",
      "color": "orange",
      "result_on_valid_code": "pass",
      "is_EU": false,
      "is_colour_code": false
    },
    {
      "name_us": "Jersey",
      "name_nl": "Jersey",
      "code": "JE",
      "color": "orange",
      "result_on_valid_code": "pass",
      "is_EU": false,
      "is_colour_code": false
    },
    {
      "name_us": "Jordan",
      "name_nl": "Jordanie",
      "code": "JO",
      "color": "orange_high_incidence",
      "result_on_valid_code": "pass",
      "is_EU": false,
      "is_colour_code": false
    },
    {
      "name_us": "Kazakhstan",
      "name_nl": "Kazachstan",
      "code": "KZ",
      "color": "orange",
      "result_on_valid_code": "pass",
      "is_EU": false,
      "is_colour_code": false
    },
    {
      "name_us": "Kenya",
      "name_nl": "Kenia",
      "code": "KE",
      "color": "orange",
      "result_on_valid_code": "pass",
      "is_EU": false,
      "is_colour_code": false
    },
    {
      "name_us": "Kiribati",
      "name_nl": "Kiribati",
      "code": "KI",
      "color": "orange",
      "result_on_valid_code": "pass",
      "is_EU": false,
      "is_colour_code": false
    },
    {
      "name_us": "Korea (Democratic People\u0027s Republic of)",
      "name_nl": "Noord-Korea",
      "code": "KP",
      "color": "orange",
      "result_on_valid_code": "pass",
      "is_EU": false,
      "is_colour_code": false
    },
    {
      "name_us": "Korea,  Republic of",
      "name_nl": "Zuid-Korea",
      "code": "KR",
      "color": "yellow",
      "result_on_valid_code": "pass",
      "is_EU": false,
      "is_colour_code": false
    },
    {
      "name_us": "Kosovo",
      "name_nl": "Kosovo",
      "code": "RS-KM",
      "color": "orange_high_incidence",
      "result_on_valid_code": "pass",
      "is_EU": false,
      "is_colour_code": false
    },
    {
      "name_us": "Kuwait",
      "name_nl": "Koeweit",
      "code": "KW",
      "color": "yellow",
      "result_on_valid_code": "pass",
      "is_EU": false,
      "is_colour_code": false
    },
    {
      "name_us": "Kyrgyzstan",
      "name_nl": "Kirgizie",
      "code": "KG",
      "color": "orange",
      "result_on_valid_code": "pass",
      "is_EU": false,
      "is_colour_code": false
    },
    {
      "name_us": "Lao People\u0027s Democratic Republic",
      "name_nl": "Laos",
      "code": "LA",
      "color": "orange",
      "result_on_valid_code": "pass",
      "is_EU": false,
      "is_colour_code": false
    },
    {
      "name_us": "Latvia",
      "name_nl": "Letland",
      "code": "LV",
      "color": "yellow",
      "result_on_valid_code": "pass",
      "is_EU": true,
      "is_colour_code": false
    },
    {
      "name_us": "Lebanon",
      "name_nl": "Libanon",
      "code": "LB",
      "color": "orange",
      "result_on_valid_code": "pass",
      "is_EU": false,
      "is_colour_code": false
    },
    {
      "name_us": "Lesotho",
      "name_nl": "Lesotho",
      "code": "LS",
      "color": "orange_high_incidence",
      "result_on_valid_code": "pass",
      "is_EU": false,
      "is_colour_code": false
    },
    {
      "name_us": "Liberia",
      "name_nl": "Liberia",
      "code": "LR",
      "color": "orange",
      "result_on_valid_code": "pass",
      "is_EU": false,
      "is_colour_code": false
    },
    {
      "name_us": "Libya",
      "name_nl": "Libie",
      "code": "LY",
      "color": "orange",
      "result_on_valid_code": "pass",
      "is_EU": false,
      "is_colour_code": false
    },
    {
      "name_us": "Liechtenstein",
      "name_nl": "Liechtenstein",
      "code": "LI",
      "color": "yellow",
      "result_on_valid_code": "pass",
      "is_EU": true,
      "is_colour_code": false
    },
    {
      "name_us": "Lithuania",
      "name_nl": "Litouwen",
      "code": "LT",
      "color": "yellow",
      "result_on_valid_code": "pass",
      "is_EU": true,
      "is_colour_code": false
    },
    {
      "name_us": "Luxembourg",
      "name_nl": "Luxemburg",
      "code": "LU",
      "color": "yellow",
      "result_on_valid_code": "pass",
      "is_EU": true,
      "is_colour_code": false
    },
    {
      "name_us": "Macao",
      "name_nl": "Macau",
      "code": "MO",
      "color": "yellow",
      "result_on_valid_code": "pass",
      "is_EU": false,
      "is_colour_code": false
    },
    {
      "name_us": "Madagascar",
      "name_nl": "Madagaskar",
      "code": "MG",
      "color": "orange",
      "result_on_valid_code": "pass",
      "is_EU": false,
      "is_colour_code": false
    },
    {
      "name_us": "Malawi",
      "name_nl": "Malawi",
      "code": "MW",
      "color": "orange_high_incidence",
      "result_on_valid_code": "pass",
      "is_EU": false,
      "is_colour_code": false
    },
    {
      "name_us": "Malaysia",
      "name_nl": "Maleisie",
      "code": "MY",
      "color": "orange",
      "result_on_valid_code": "pass",
      "is_EU": false,
      "is_colour_code": false
    },
    {
      "name_us": "Maldives",
      "name_nl": "Malediven",
      "code": "MV",
      "color": "orange",
      "result_on_valid_code": "pass",
      "is_EU": false,
      "is_colour_code": false
    },
    {
      "name_us": "Mali",
      "name_nl": "Mali",
      "code": "ML",
      "color": "orange",
      "result_on_valid_code": "pass",
      "is_EU": false,
      "is_colour_code": false
    },
    {
      "name_us": "Malta",
      "name_nl": "Malta",
      "code": "MT",
      "color": "yellow",
      "result_on_valid_code": "pass",
      "is_EU": true,
      "is_colour_code": false
    },
    {
      "name_us": "Marshall Islands",
      "name_nl": "Marshalleilanden",
      "code": "MH",
      "color": "orange",
      "result_on_valid_code": "pass",
      "is_EU": false,
      "is_colour_code": false
    },
    {
      "name_us": "Martinique",
      "name_nl": "Martinique",
      "code": "MQ",
      "color": "orange_high_incidence",
      "result_on_valid_code": "pass",
      "is_EU": true,
      "is_colour_code": false
    },
    {
      "name_us": "Mauritania",
      "name_nl": "Mauritanie",
      "code": "MR",
      "color": "orange",
      "result_on_valid_code": "pass",
      "is_EU": false,
      "is_colour_code": false
    },
    {
      "name_us": "Mauritius",
      "name_nl": "Mauritius",
      "code": "MU",
      "color": "orange_high_incidence",
      "result_on_valid_code": "pass",
      "is_EU": false,
      "is_colour_code": false
    },
    {
      "name_us": "Mayotte",
      "name_nl": "Mayotte",
      "code": "YT",
      "color": "orange",
      "result_on_valid_code": "pass",
      "is_EU": true,
      "is_colour_code": false
    },
    {
      "name_us": "Mexico",
      "name_nl": "Mexico",
      "code": "MX",
      "color": "orange",
      "result_on_valid_code": "pass",
      "is_EU": false,
      "is_colour_code": false
    },
    {
      "name_us": "Micronesia (Federated States of)",
      "name_nl": "Micronesia",
      "code": "FM",
      "color": "orange",
      "result_on_valid_code": "pass",
      "is_EU": false,
      "is_colour_code": false
    },
    {
      "name_us": "Moldova (the Republic of)",
      "name_nl": "Moldavie",
      "code": "MD",
      "color": "orange",
      "result_on_valid_code": "pass",
      "is_EU": false,
      "is_colour_code": false
    },
    {
      "name_us": "Monaco",
      "name_nl": "Monaco",
      "code": "MC",
      "color": "yellow",
      "result_on_valid_code": "pass",
      "is_EU": true,
      "is_colour_code": false
    },
    {
      "name_us": "Mongolia",
      "name_nl": "Mongolie",
      "code": "MN",
      "color": "orange",
      "result_on_valid_code": "pass",
      "is_EU": false,
      "is_colour_code": false
    },
    {
      "name_us": "Montenegro",
      "name_nl": "Montenegro",
      "code": "ME",
      "color": "orange_high_incidence",
      "result_on_valid_code": "pass",
      "is_EU": false,
      "is_colour_code": false
    },
    {
      "name_us": "Montserrat",
      "name_nl": "Montserrat",
      "code": "MS",
      "color": "orange",
      "result_on_valid_code": "pass",
      "is_EU": false,
      "is_colour_code": false
    },
    {
      "name_us": "Morocco",
      "name_nl": "Marokko",
      "code": "MA",
      "color": "orange",
      "result_on_valid_code": "pass",
      "is_EU": false,
      "is_colour_code": false
    },
    {
      "name_us": "Mozambique",
      "name_nl": "Mozambique",
      "code": "MZ",
      "color": "orange_high_incidence",
      "result_on_valid_code": "pass",
      "is_EU": false,
      "is_colour_code": false
    },
    {
      "name_us": "Myanmar",
      "name_nl": "Myanmar",
      "code": "MM",
      "color": "orange",
      "result_on_valid_code": "pass",
      "is_EU": false,
      "is_colour_code": false
    },
    {
      "name_us": "Namibia",
      "name_nl": "Namibie",
      "code": "NA",
      "color": "orange_high_incidence",
      "result_on_valid_code": "pass",
      "is_EU": false,
      "is_colour_code": false
    },
    {
      "name_us": "Nauru",
      "name_nl": "Nauru",
      "code": "NR",
      "color": "orange",
      "result_on_valid_code": "pass",
      "is_EU": false,
      "is_colour_code": false
    },
    {
      "name_us": "Nepal",
      "name_nl": "Nepal",
      "code": "NP",
      "color": "orange",
      "result_on_valid_code": "pass",
      "is_EU": false,
      "is_colour_code": false
    },
    {
      "name_us": "Netherlands",
      "name_nl": "Nederland",
      "code": "NL",
      "color": "yellow",
      "result_on_valid_code": "nl_rules",
      "is_EU": true,
      "is_colour_code": false
    },
    {
      "name_us": "New Caledonia",
      "name_nl": "Nieuw-Caledonie",
      "code": "NC",
      "color": "orange",
      "result_on_valid_code": "pass",
      "is_EU": false,
      "is_colour_code": false
    },
    {
      "name_us": "New Zealand",
      "name_nl": "Nieuw-Zeeland",
      "code": "NZ",
      "color": "yellow",
      "result_on_valid_code": "pass",
      "is_EU": false,
      "is_colour_code": false
    },
    {
      "name_us": "Nicaragua",
      "name_nl": "Nicaragua",
      "code": "NI",
      "color": "orange",
      "result_on_valid_code": "pass",
      "is_EU": false,
      "is_colour_code": false
    },
    {
      "name_us": "Niger",
      "name_nl": "Niger",
      "code": "NE",
      "color": "orange",
      "result_on_valid_code": "pass",
      "is_EU": false,
      "is_colour_code": false
    },
    {
      "name_us": "Nigeria",
      "name_nl": "Nigeria",
      "code": "NG",
      "color": "orange_high_incidence",
      "result_on_valid_code": "pass",
      "is_EU": false,
      "is_colour_code": false
    },
    {
      "name_us": "Niue",
      "name_nl": "Niue",
      "code": "NU",
      "color": "orange",
      "result_on_valid_code": "pass",
      "is_EU": false,
      "is_colour_code": false
    },
    {
      "name_us": "Norfolk Island",
      "name_nl": "Norfolk",
      "code": "NF",
      "color": "orange",
      "result_on_valid_code": "pass",
      "is_EU": false,
      "is_colour_code": false
    },
    {
      "name_us": "North Macedonia",
      "name_nl": "Noord-Macedonie",
      "code": "MK",
      "color": "orange",
      "result_on_valid_code": "pass",
      "is_EU": false,
      "is_colour_code": false
    },
    {
      "name_us": "Northern Mariana Islands",
      "name_nl": "Noordelijke Marianen",
      "code": "MP",
      "color": "orange",
      "result_on_valid_code": "pass",
      "is_EU": false,
      "is_colour_code": false
    },
    {
      "name_us": "Norway",
      "name_nl": "Noorwegen",
      "code": "NO",
      "color": "yellow",
      "result_on_valid_code": "pass",
      "is_EU": true,
      "is_colour_code": false
    },
    {
      "name_us": "Oman",
      "name_nl": "Oman",
      "code": "OM",
      "color": "orange",
      "result_on_valid_code": "pass",
      "is_EU": false,
      "is_colour_code": false
    },
    {
      "name_us": "Pakistan",
      "name_nl": "Pakistan",
      "code": "PK",
      "color": "orange",
      "result_on_valid_code": "pass",
      "is_EU": false,
      "is_colour_code": false
    },
    {
      "name_us": "Palau",
      "name_nl": "Palau",
      "code": "PW",
      "color": "orange",
      "result_on_valid_code": "pass",
      "is_EU": false,
      "is_colour_code": false
    },
    {
      "name_us": "Palestine,  State of",
      "name_nl": "Palestina",
      "code": "PS",
      "color": "orange",
      "result_on_valid_code": "pass",
      "is_EU": false,
      "is_colour_code": false
    },
    {
      "name_us": "Panama",
      "name_nl": "Panama",
      "code": "PA",
      "color": "orange",
      "result_on_valid_code": "pass",
      "is_EU": false,
      "is_colour_code": false
    },
    {
      "name_us": "Papua New Guinea",
      "name_nl": "Papoea-Nieuw-Guinea",
      "code": "PG",
      "color": "orange",
      "result_on_valid_code": "pass",
      "is_EU": false,
      "is_colour_code": false
    },
    {
      "name_us": "Paraguay",
      "name_nl": "Paraguay",
      "code": "PY",
      "color": "orange",
      "result_on_valid_code": "pass",
      "is_EU": false,
      "is_colour_code": false
    },
    {
      "name_us": "Peru",
      "name_nl": "Peru",
      "code": "PE",
      "color": "yellow",
      "result_on_valid_code": "pass",
      "is_EU": false,
      "is_colour_code": false
    },
    {
      "name_us": "Philippines",
      "name_nl": "Filipijnen",
      "code": "PH",
      "color": "orange",
      "result_on_valid_code": "pass",
      "is_EU": false,
      "is_colour_code": false
    },
    {
      "name_us": "Pitcairn",
      "name_nl": "Pitcairneilanden",
      "code": "PN",
      "color": "orange",
      "result_on_valid_code": "pass",
      "is_EU": false,
      "is_colour_code": false
    },
    {
      "name_us": "Poland",
      "name_nl": "Polen",
      "code": "PL",
      "color": "yellow",
      "result_on_valid_code": "pass",
      "is_EU": true,
      "is_colour_code": false
    },
    {
      "name_us": "Portugal",
      "name_nl": "Portugal",
      "code": "PT",
      "color": "yellow",
      "result_on_valid_code": "pass",
      "is_EU": true,
      "is_colour_code": false
    },
    {
      "name_us": "Portugal,  Azores",
      "name_nl": "Portugal,  Azoren",
      "code": "PT-20",
      "color": "yellow",
      "result_on_valid_code": "pass",
      "is_EU": true,
      "is_colour_code": false
    },
    {
      "name_us": "Portugal,  Madeira",
      "name_nl": "Portugal,  Madeira",
      "code": "PT-30",
      "color": "yellow",
      "result_on_valid_code": "pass",
      "is_EU": true,
      "is_colour_code": false
    },
    {
      "name_us": "Puerto Rico",
      "name_nl": "Puerto Rico",
      "code": "PR",
      "color": "orange_high_incidence",
      "result_on_valid_code": "pass",
      "is_EU": false,
      "is_colour_code": false
    },
    {
      "name_us": "Qatar",
      "name_nl": "Qatar",
      "code": "QA",
      "color": "yellow",
      "result_on_valid_code": "pass",
      "is_EU": false,
      "is_colour_code": false
    },
    {
      "name_us": "Reunion",
      "name_nl": "Reunion",
      "code": "RE",
      "color": "orange",
      "result_on_valid_code": "pass",
      "is_EU": true,
      "is_colour_code": false
    },
    {
      "name_us": "Romania",
      "name_nl": "Roemenie",
      "code": "RO",
      "color": "yellow",
      "result_on_valid_code": "pass",
      "is_EU": true,
      "is_colour_code": false
    },
    {
      "name_us": "Russian Federation",
      "name_nl": "Rusland",
      "code": "RU",
      "color": "orange",
      "result_on_valid_code": "pass",
      "is_EU": false,
      "is_colour_code": false
    },
    {
      "name_us": "Rwanda",
      "name_nl": "Rwanda",
      "code": "RW",
      "color": "yellow",
      "result_on_valid_code": "pass",
      "is_EU": false,
      "is_colour_code": false
    },
    {
      "name_us": "Saba",
      "name_nl": "Saba",
      "code": "BQ-2",
      "color": "yellow",
      "result_on_valid_code": "pass",
      "is_EU": true,
      "is_colour_code": false
    },
    {
      "name_us": "Saint Barthelemy",
      "name_nl": "Saint-Barthelemy",
      "code": "BL",
      "color": "orange",
      "result_on_valid_code": "pass",
      "is_EU": false,
      "is_colour_code": false
    },
    {
      "name_us": "Saint Helena,  Ascension and Tristan da Cunha[b]",
      "name_nl": "Sint-Helena,  Ascension en Tristan da Cunha",
      "code": "SH",
      "color": "orange",
      "result_on_valid_code": "pass",
      "is_EU": false,
      "is_colour_code": false
    },
    {
      "name_us": "Saint Kitts and Nevis",
      "name_nl": "Saint Kitts en Nevis",
      "code": "KN",
      "color": "orange",
      "result_on_valid_code": "pass",
      "is_EU": false,
      "is_colour_code": false
    },
    {
      "name_us": "Saint Lucia",
      "name_nl": "Saint Lucia",
      "code": "LC",
      "color": "orange",
      "result_on_valid_code": "pass",
      "is_EU": false,
      "is_colour_code": false
    },
    {
      "name_us": "Saint Martin (Dutch part)",
      "name_nl": "Sint-Maarten (Nederlands deel)",
      "code": "SX",
      "color": "yellow",
      "result_on_valid_code": "pass",
      "is_EU": true,
      "is_colour_code": false
    },
    {
      "name_us": "Saint Martin (French part)",
      "name_nl": "Sint-Maarten (Frans deel)",
      "code": "MF",
      "color": "orange",
      "result_on_valid_code": "pass",
      "is_EU": true,
      "is_colour_code": false
    },
    {
      "name_us": "Saint Pierre and Miquelon",
      "name_nl": "Saint-Pierre en Miquelon",
      "code": "PM",
      "color": "orange",
      "result_on_valid_code": "pass",
      "is_EU": false,
      "is_colour_code": false
    },
    {
      "name_us": "Saint Vincent and the Grenadines",
      "name_nl": "Saint Vincent en de Grenadines",
      "code": "VC",
      "color": "orange",
      "result_on_valid_code": "pass",
      "is_EU": false,
      "is_colour_code": false
    },
    {
      "name_us": "Samoa",
      "name_nl": "Samoa",
      "code": "WS",
      "color": "orange",
      "result_on_valid_code": "pass",
      "is_EU": false,
      "is_colour_code": false
    },
    {
      "name_us": "San Marino",
      "name_nl": "San Marino",
      "code": "SM",
      "color": "green",
      "result_on_valid_code": "pass",
      "is_EU": true,
      "is_colour_code": false
    },
    {
      "name_us": "Sao Tome and Principe",
      "name_nl": "Sao Tome en Principe",
      "code": "ST",
      "color": "orange",
      "result_on_valid_code": "pass",
      "is_EU": false,
      "is_colour_code": false
    },
    {
      "name_us": "Saudi Arabia",
      "name_nl": "Saudi Arabie",
      "code": "SA",
      "color": "yellow",
      "result_on_valid_code": "pass",
      "is_EU": false,
      "is_colour_code": false
    },
    {
      "name_us": "Senegal",
      "name_nl": "Senegal",
      "code": "SN",
      "color": "orange",
      "result_on_valid_code": "pass",
      "is_EU": false,
      "is_colour_code": false
    },
    {
      "name_us": "Serbia",
      "name_nl": "Servie",
      "code": "RS",
      "color": "orange",
      "result_on_valid_code": "pass",
      "is_EU": false,
      "is_colour_code": false
    },
    {
      "name_us": "Seychelles",
      "name_nl": "Seychellen",
      "code": "SC",
      "color": "orange",
      "result_on_valid_code": "pass",
      "is_EU": false,
      "is_colour_code": false
    },
    {
      "name_us": "Sierra Leone",
      "name_nl": "Sierra Leone",
      "code": "SL",
      "color": "orange",
      "result_on_valid_code": "pass",
      "is_EU": false,
      "is_colour_code": false
    },
    {
      "name_us": "Singapore",
      "name_nl": "Singapore",
      "code": "SG",
      "color": "orange",
      "result_on_valid_code": "pass",
      "is_EU": false,
      "is_colour_code": false
    },
    {
      "name_us": "Sint Eustatius",
      "name_nl": "Sint Eustatius",
      "code": "BQ-3",
      "color": "yellow",
      "result_on_valid_code": "pass",
      "is_EU": true,
      "is_colour_code": false
    },
    {
      "name_us": "Slovakia",
      "name_nl": "Slowakije",
      "code": "SK",
      "color": "yellow",
      "result_on_valid_code": "pass",
      "is_EU": true,
      "is_colour_code": false
    },
    {
      "name_us": "Slovenia",
      "name_nl": "Slovenie",
      "code": "SI",
      "color": "yellow",
      "result_on_valid_code": "pass",
      "is_EU": true,
      "is_colour_code": false
    },
    {
      "name_us": "Solomon Islands",
      "name_nl": "Salomonseilanden",
      "code": "SB",
      "color": "orange",
      "result_on_valid_code": "pass",
      "is_EU": false,
      "is_colour_code": false
    },
    {
      "name_us": "Somalia",
      "name_nl": "Somalie",
      "code": "SO",
      "color": "orange_high_incidence",
      "result_on_valid_code": "pass",
      "is_EU": false,
      "is_colour_code": false
    },
    {
      "name_us": "South Africa",
      "name_nl": "Zuid-Afrika",
      "code": "ZA",
      "color": "orange_high_incidence",
      "result_on_valid_code": "pass",
      "is_EU": false,
      "is_colour_code": false
    },
    {
      "name_us": "South Georgia and the South Sandwich Islands",
      "name_nl": "Zuid-Georgia en de Zuidelijke Sandwicheilanden",
      "code": "GS",
      "color": "orange",
      "result_on_valid_code": "pass",
      "is_EU": false,
      "is_colour_code": false
    },
    {
      "name_us": "South Sudan",
      "name_nl": "Zuid-Soedan",
      "code": "SS",
      "color": "orange",
      "result_on_valid_code": "pass",
      "is_EU": false,
      "is_colour_code": false
    },
    {
      "name_us": "Spain",
      "name_nl": "Spanje",
      "code": "ES",
      "color": "yellow",
      "result_on_valid_code": "pass",
      "is_EU": true,
      "is_colour_code": false
    },
    {
      "name_us": "Canary Islands",
      "name_nl": "Canarische eilanden",
      "code": "IC",
      "color": "yellow",
      "result_on_valid_code": "pass",
      "is_EU": true,
      "is_colour_code": false
    },
    {
      "name_us": "Sri Lanka",
      "name_nl": "Sri Lanka",
      "code": "LK",
      "color": "orange",
      "result_on_valid_code": "pass",
      "is_EU": false,
      "is_colour_code": false
    },
    {
      "name_us": "Sudan",
      "name_nl": "Soedan",
      "code": "SD",
      "color": "orange",
      "result_on_valid_code": "pass",
      "is_EU": false,
      "is_colour_code": false
    },
    {
      "name_us": "Suriname",
      "name_nl": "Suriname",
      "code": "SR",
      "color": "orange",
      "result_on_valid_code": "pass",
      "is_EU": false,
      "is_colour_code": false
    },
    {
      "name_us": "Svalbard and Jan Mayen[c]",
      "name_nl": "Spitsbergen en Jan Mayen",
      "code": "SJ",
      "color": "yellow",
      "result_on_valid_code": "pass",
      "is_EU": false,
      "is_colour_code": false
    },
    {
      "name_us": "Sweden",
      "name_nl": "Zweden",
      "code": "SE",
      "color": "yellow",
      "result_on_valid_code": "pass",
      "is_EU": true,
      "is_colour_code": false
    },
    {
      "name_us": "Switzerland",
      "name_nl": "Zwitserland",
      "code": "CH",
      "color": "green",
      "result_on_valid_code": "pass",
      "is_EU": true,
      "is_colour_code": false
    },
    {
      "name_us": "Syrian Arab Republic",
      "name_nl": "Syrie",
      "code": "SY",
      "color": "orange",
      "result_on_valid_code": "pass",
      "is_EU": false,
      "is_colour_code": false
    },
    {
      "name_us": "Taiwan",
      "name_nl": "Taiwan",
      "code": "TW",
      "color": "yellow",
      "result_on_valid_code": "pass",
      "is_EU": false,
      "is_colour_code": false
    },
    {
      "name_us": "Tajikistan",
      "name_nl": "Tadzjikistan",
      "code": "TJ",
      "color": "orange",
      "result_on_valid_code": "pass",
      "is_EU": false,
      "is_colour_code": false
    },
    {
      "name_us": "Tanzania,  United Republic of",
      "name_nl": "Tanzania",
      "code": "TZ",
      "color": "orange",
      "result_on_valid_code": "pass",
      "is_EU": false,
      "is_colour_code": false
    },
    {
      "name_us": "Thailand",
      "name_nl": "Thailand",
      "code": "TH",
      "color": "orange",
      "result_on_valid_code": "pass",
      "is_EU": false,
      "is_colour_code": false
    },
    {
      "name_us": "Timor-Leste",
      "name_nl": "Oost-Timor",
      "code": "TL",
      "color": "orange",
      "result_on_valid_code": "pass",
      "is_EU": false,
      "is_colour_code": false
    },
    {
      "name_us": "Togo",
      "name_nl": "Togo",
      "code": "TG",
      "color": "orange",
      "result_on_valid_code": "pass",
      "is_EU": false,
      "is_colour_code": false
    },
    {
      "name_us": "Tokelau",
      "name_nl": "Tokelau",
      "code": "TK",
      "color": "orange",
      "result_on_valid_code": "pass",
      "is_EU": false,
      "is_colour_code": false
    },
    {
      "name_us": "Tonga",
      "name_nl": "Tonga",
      "code": "TO",
      "color": "orange",
      "result_on_valid_code": "pass",
      "is_EU": false,
      "is_colour_code": false
    },
    {
      "name_us": "Trinidad and Tobago",
      "name_nl": "Trinidad en Tobago",
      "code": "TT",
      "color": "orange_high_incidence",
      "result_on_valid_code": "pass",
      "is_EU": false,
      "is_colour_code": false
    },
    {
      "name_us": "Tunisia",
      "name_nl": "Tunesie",
      "code": "TN",
      "color": "orange",
      "result_on_valid_code": "pass",
      "is_EU": false,
      "is_colour_code": false
    },
    {
      "name_us": "Turkey",
      "name_nl": "Turkije",
      "code": "TR",
      "color": "orange",
      "result_on_valid_code": "pass",
      "is_EU": false,
      "is_colour_code": false
    },
    {
      "name_us": "Turkmenistan",
      "name_nl": "Turkmenistan",
      "code": "TM",
      "color": "orange",
      "result_on_valid_code": "pass",
      "is_EU": false,
      "is_colour_code": false
    },
    {
      "name_us": "Turks and Caicos Islands",
      "name_nl": "Turks- en Caicoseilanden",
      "code": "TC",
      "color": "orange",
      "result_on_valid_code": "pass",
      "is_EU": false,
      "is_colour_code": false
    },
    {
      "name_us": "Tuvalu",
      "name_nl": "Tuvalu",
      "code": "TV",
      "color": "orange",
      "result_on_valid_code": "pass",
      "is_EU": false,
      "is_colour_code": false
    },
    {
      "name_us": "Uganda",
      "name_nl": "Oeganda",
      "code": "UG",
      "color": "orange",
      "result_on_valid_code": "pass",
      "is_EU": false,
      "is_colour_code": false
    },
    {
      "name_us": "Ukraine",
      "name_nl": "Oekraine",
      "code": "UA",
      "color": "orange",
      "result_on_valid_code": "pass",
      "is_EU": false,
      "is_colour_code": false
    },
    {
      "name_us": "United Arab Emirates",
      "name_nl": "Verenigde Arabische Emiraten",
      "code": "AE",
      "color": "yellow",
      "result_on_valid_code": "pass",
      "is_EU": false,
      "is_colour_code": false
    },
    {
      "name_us": "United Kingdom of Great Britain and Northern Ireland",
      "name_nl": "Verenigd Koninkrijk",
      "code": "GB",
      "color": "orange_high_incidence",
      "result_on_valid_code": "pass",
      "is_EU": false,
      "is_colour_code": false
    },
    {
      "name_us": "United States Minor Outlying Islands[e]",
      "name_nl": "Kleine afgelegen eilanden van de Verenigde Staten",
      "code": "UM",
      "color": "orange",
      "result_on_valid_code": "pass",
      "is_EU": false,
      "is_colour_code": false
    },
    {
      "name_us": "United States of America",
      "name_nl": "Verenigde Staten",
      "code": "US",
      "color": "orange_high_incidence",
      "result_on_valid_code": "pass",
      "is_EU": false,
      "is_colour_code": false
    },
    {
      "name_us": "Uruguay",
      "name_nl": "Uruguay",
      "code": "UY",
      "color": "yellow",
      "result_on_valid_code": "pass",
      "is_EU": false,
      "is_colour_code": false
    },
    {
      "name_us": "Uzbekistan",
      "name_nl": "Oezbekistan",
      "code": "UZ",
      "color": "orange",
      "result_on_valid_code": "pass",
      "is_EU": false,
      "is_colour_code": false
    },
    {
      "name_us": "Vanuatu",
      "name_nl": "Vanuatu",
      "code": "VU",
      "color": "orange",
      "result_on_valid_code": "pass",
      "is_EU": false,
      "is_colour_code": false
    },
    {
      "name_us": "Vatican City State (Holy See)",
      "name_nl": "Vaticaanstad",
      "code": "VA",
      "color": "green",
      "result_on_valid_code": "pass",
      "is_EU": true,
      "is_colour_code": false
    },
    {
      "name_us": "Venezuela (Bolivarian Republic of)",
      "name_nl": "Venezuela",
      "code": "VE",
      "color": "orange_high_incidence",
      "result_on_valid_code": "pass",
      "is_EU": false,
      "is_colour_code": false
    },
    {
      "name_us": "Viet Nam",
      "name_nl": "Vietnam",
      "code": "VN",
      "color": "orange",
      "result_on_valid_code": "pass",
      "is_EU": false,
      "is_colour_code": false
    },
    {
      "name_us": "Virgin Islands (British)",
      "name_nl": "Britse Maagdeneilanden",
      "code": "VG",
      "color": "orange",
      "result_on_valid_code": "pass",
      "is_EU": false,
      "is_colour_code": false
    },
    {
      "name_us": "Virgin Islands (U.S.)",
      "name_nl": "Amerikaanse Maagdeneilanden",
      "code": "VI",
      "color": "orange",
      "result_on_valid_code": "pass",
      "is_EU": false,
      "is_colour_code": false
    },
    {
      "name_us": "Wallis and Futuna",
      "name_nl": "Wallis en Futuna",
      "code": "WF",
      "color": "orange",
      "result_on_valid_code": "pass",
      "is_EU": false,
      "is_colour_code": false
    },
    {
      "name_us": "Western Sahara",
      "name_nl": "Westelijke Sahara/SADR",
      "code": "EH",
      "color": "orange",
      "result_on_valid_code": "pass",
      "is_EU": false,
      "is_colour_code": false
    },
    {
      "name_us": "Yemen",
      "name_nl": "Jemen",
      "code": "YE",
      "color": "orange",
      "result_on_valid_code": "pass",
      "is_EU": false,
      "is_colour_code": false
    },
    {
      "name_us": "Zambia",
      "name_nl": "Zambia",
      "code": "ZM",
      "color": "orange",
      "result_on_valid_code": "pass",
      "is_EU": false,
      "is_colour_code": false
    },
    {
      "name_us": "Zimbabwe",
      "name_nl": "Zimbabwe",
      "code": "ZW",
      "color": "orange_high_incidence",
      "result_on_valid_code": "pass",
      "is_EU": false,
      "is_colour_code": false
    }
  ]
}
